Workbook

Sheet DASHBOARD
A1: DASHBOARD
B5: TOTAL PRODUCTOS | D5: CATEGORÍAS | F5: PROVEEDORES | H5: COSTO TOTAL EST.
B6: =COUNTA('CONSOLIDADO PRECIOS'!B$5:B$646)-COUNTIF('CONSOLIDADO PRECIOS'!B$5:B$646,"") -> 574 | D6: =COUNTA(RESUMEN!A3:A36) -> 34 | F6: =COUNTA(PROVEEDORES!A3:A42) -> 40 | H6: =RESUMEN!D37 -> 8279311.2
B8: Factor de incremento: | D8: ='CONSOLIDADO PRECIOS'!B2 -> 0.1
B10: COSTO ESTIMADO TOTAL POR CATEGORÍA
B11: CATEGORÍA | D11: N° PROD. | F11: PROM. ESTIMADO | H11: TOTAL ESTIMADO
B12: =RESUMEN!A3 -> ABARROTE | D12: =RESUMEN!B3 -> 240 | F12: =RESUMEN!C3 -> 18165.546 | H12: =RESUMEN!D3 -> 4341565.4
B13: =RESUMEN!A4 -> AGUA | D13: =RESUMEN!B4 -> 3 | F13: =RESUMEN!C4 -> 7667 | H13: =RESUMEN!D4 -> 15334
B14: =RESUMEN!A5 -> ALGAS | D14: =RESUMEN!B5 -> 2 | F14: =RESUMEN!C5 -> 9824.8333 | H14: =RESUMEN!D5 -> 9824.8333
B15: =RESUMEN!A6 -> ARTICULO COCINA | D15: =RESUMEN!B6 -> 35 | F15: =RESUMEN!C6 -> 2572.2529 | H15: =RESUMEN!D6 -> 87456.6
B16: =RESUMEN!A7 -> BROTES | D16: =RESUMEN!B7 -> 2 | F16: =RESUMEN!C7 -> 3575.3667 | H16: =RESUMEN!D7 -> 3575.3667
B17: =RESUMEN!A8 -> CABRITO | D17: =RESUMEN!B8 -> 2 | F17: =RESUMEN!C8 -> 24334.567 | H17: =RESUMEN!D8 -> 24334.567
B18: =RESUMEN!A9 -> CERDO | D18: =RESUMEN!B9 -> 22 | F18: =RESUMEN!C9 -> 14539.905 | H18: =RESUMEN!D9 -> 305338
B19: =RESUMEN!A10 -> CERVEZA | D19: =RESUMEN!B10 -> 2 | F19: =RESUMEN!C10 -> 5725.5 | H19: =RESUMEN!D10 -> 5725.5
B20: =RESUMEN!A11 -> CHOCOLATE | D20: =RESUMEN!B11 -> 22 | F20: =RESUMEN!C11 -> 17098.417 | H20: =RESUMEN!D11 -> 359066.77
B21: =RESUMEN!A12 -> COLORANTES | D21: =RESUMEN!B12 -> 14 | F21: =RESUMEN!C12 -> 19172.69 | H21: =RESUMEN!D12 -> 249244.97
B22: =RESUMEN!A13 -> CONGELADO | D22: =RESUMEN!B13 -> 14 | F22: =RESUMEN!C13 -> 5833.1731 | H22: =RESUMEN!D13 -> 75831.25
B23: =RESUMEN!A14 -> CONSERVA | D23: =RESUMEN!B14 -> 5 | F23: =RESUMEN!C14 -> 5490.5583 | H23: =RESUMEN!D14 -> 21962.233
... B45: =RESUMEN!A36 -> YOGURT | D45: =RESUMEN!B36 -> 4 | F45: =RESUMEN!C36 -> 3064.8444 | H45: =RESUMEN!D36 -> 9194.5333
B46: TOTAL | D46: =RESUMEN!B37 -> 642 | H46: =RESUMEN!D37 -> 8279311.2
B48: TOP 10 — PRODUCTOS CON MAYOR PRECIO ESTIMADO
B49: INGREDIENTE | E49: CATEGORÍA | H49: PRECIO ESTIMADO
B50: =IFERROR(INDEX('CONSOLIDADO PRECIOS'!$B$5:$B$646,MATCH(LARGE('CONSOLIDADO PRECIOS'!$U$5:$U$646,1),'CONSOLIDADO PRECIOS'!$U$5:$U$646,0)),"") -> BAYAS DE ENEBRO | E50: =IFERROR(INDEX('CONSOLIDADO PRECIOS'!$A$5:$A$646,MATCH(LARGE('CONSOLIDADO PRECIOS'!$U$5:$U$646,1),'CONSOLIDADO PRECIOS'!$U$5:$U$646,0)),"") -> FRUTA VERDURA | H50: =IFERROR(LARGE('CONSOLIDADO PRECIOS'!$U$5:$U$646,1),"") -> 250252.2
B51: =IFERROR(INDEX('CONSOLIDADO PRECIOS'!$B$5:$B$646,MATCH(LARGE('CONSOLIDADO PRECIOS'!$U$5:$U$646,2),'CONSOLIDADO PRECIOS'!$U$5:$U$646,0)),"") -> FRAMBUESA LIOFILIZADA | E51: =IFERROR(INDEX('CONSOLIDADO PRECIOS'!$A$5:$A$646,MATCH(LARGE('CONSOLIDADO PRECIOS'!$U$5:$U$646,2),'CONSOLIDADO PRECIOS'!$U$5:$U$646,0)),"") -> ABARROTE | H51: =IFERROR(LARGE('CONSOLIDADO PRECIOS'!$U$5:$U$646,2),"") -> 173730.7
B52: =IFERROR(INDEX('CONSOLIDADO PRECIOS'!$B$5:$B$646,MATCH(LARGE('CONSOLIDADO PRECIOS'!$U$5:$U$646,3),'CONSOLIDADO PRECIOS'!$U$5:$U$646,0)),"") -> MARACUYA CRISPY | E52: =IFERROR(INDEX('CONSOLIDADO PRECIOS'!$A$5:$A$646,MATCH(LARGE('CONSOLIDADO PRECIOS'!$U$5:$U$646,3),'CONSOLIDADO PRECIOS'!$U$5:$U$646,0)),"") -> ABARROTE | H52: =IFERROR(LARGE('CONSOLIDADO PRECIOS'!$U$5:$U$646,3),"") -> 170623.2
B53: =IFERROR(INDEX('CONSOLIDADO PRECIOS'!$B$5:$B$646,MATCH(LARGE('CONSOLIDADO PRECIOS'!$U$5:$U$646,4),'CONSOLIDADO PRECIOS'!$U$5:$U$646,0)),"") -> POTATOWHIP | E53: =IFERROR(INDEX('CONSOLIDADO PRECIOS'!$A$5:$A$646,MATCH(LARGE('CONSOLIDADO PRECIOS'!$U$5:$U$646,4),'CONSOLIDADO PRECIOS'!$U$5:$U$646,0)),"") -> ABARROTE | H53: =IFERROR(LARGE('CONSOLIDADO PRECIOS'!$U$5:$U$646,4),"") -> 157881.17
B54: =IFERROR(INDEX('CONSOLIDADO PRECIOS'!$B$5:$B$646,MATCH(LARGE('CONSOLIDADO PRECIOS'!$U$5:$U$646,5),'CONSOLIDADO PRECIOS'!$U$5:$U$646,0)),"") -> ESENCIA DE FRAMBUESA | E54: =IFERROR(INDEX('CONSOLIDADO PRECIOS'!$A$5:$A$646,MATCH(LARGE('CONSOLIDADO PRECIOS'!$U$5:$U$646,5),'CONSOLIDADO PRECIOS'!$U$5:$U$646,0)),"") -> ABARROTE | H54: =IFERROR(LARGE('CONSOLIDADO PRECIOS'!$U$5:$U$646,5),"") -> 130162.27
B55: =IFERROR(INDEX('CONSOLIDADO PRECIOS'!$B$5:$B$646,MATCH(LARGE('CONSOLIDADO PRECIOS'!$U$5:$U$646,6),'CONSOLIDADO PRECIOS'!$U$5:$U$646,0)),"") -> ESENCIA DE PIÑA | E55: =IFERROR(INDEX('CONSOLIDADO PRECIOS'!$A$5:$A$646,MATCH(LARGE('CONSOLIDADO PRECIOS'!$U$5:$U$646,6),'CONSOLIDADO PRECIOS'!$U$5:$U$646,0)),"") -> ABARROTE | H55: =IFERROR(LARGE('CONSOLIDADO PRECIOS'!$U$5:$U$646,6),"") -> 128711
B56: =IFERROR(INDEX('CONSOLIDADO PRECIOS'!$B$5:$B$646,MATCH(LARGE('CONSOLIDADO PRECIOS'!$U$5:$U$646,7),'CONSOLIDADO PRECIOS'!$U$5:$U$646,0)),"") -> ALGINATO DE SODIO | E56: =IFERROR(INDEX('CONSOLIDADO PRECIOS'!$A$5:$A$646,MATCH(LARGE('CONSOLIDADO PRECIOS'!$U$5:$U$646,7),'CONSOLIDADO PRECIOS'!$U$5:$U$646,0)),"") -> ABARROTE | H56: =IFERROR(LARGE('CONSOLIDADO PRECIOS'!$U$5:$U$646,7),"") -> 114726.7
B57: =IFERROR(INDEX('CONSOLIDADO PRECIOS'!$B$5:$B$646,MATCH(LARGE('CONSOLIDADO PRECIOS'!$U$5:$U$646,8),'CONSOLIDADO PRECIOS'!$U$5:$U$646,0)),"") -> GOMA KAPPA | E57: =IFERROR(INDEX('CONSOLIDADO PRECIOS'!$A$5:$A$646,MATCH(LARGE('CONSOLIDADO PRECIOS'!$U$5:$U$646,8),'CONSOLIDADO PRECIOS'!$U$5:$U$646,0)),"") -> ABARROTE | H57: =IFERROR(LARGE('CONSOLIDADO PRECIOS'!$U$5:$U$646,8),"") -> 95434.533
B58: =IFERROR(INDEX('CONSOLIDADO PRECIOS'!$B$5:$B$646,MATCH(LARGE('CONSOLIDADO PRECIOS'!$U$5:$U$646,9),'CONSOLIDADO PRECIOS'!$U$5:$U$646,0)),"") -> PEPERONCCINO O CHILE EN HOJUELAS | E58: =IFERROR(INDEX('CONSOLIDADO PRECIOS'!$A$5:$A$646,MATCH(LARGE('CONSOLIDADO PRECIOS'!$U$5:$U$646,9),'CONSOLIDADO PRECIOS'!$U$5:$U$646,0)),"") -> ABARROTE | H58: =IFERROR(LARGE('CONSOLIDADO PRECIOS'!$U$5:$U$646,9),"") -> 94822.933
B59: =IFERROR(INDEX('CONSOLIDADO PRECIOS'!$B$5:$B$646,MATCH(LARGE('CONSOLIDADO PRECIOS'!$U$5:$U$646,10),'CONSOLIDADO PRECIOS'!$U$5:$U$646,0)),"") -> TE MATCHA | E59: =IFERROR(INDEX('CONSOLIDADO PRECIOS'!$A$5:$A$646,MATCH(LARGE('CONSOLIDADO PRECIOS'!$U$5:$U$646,10),'CONSOLIDADO PRECIOS'!$U$5:$U$646,0)),"") -> TE | H59: =IFERROR(LARGE('CONSOLIDADO PRECIOS'!$U$5:$U$646,10),"") -> 92763.733

Sheet PROVEEDORES
A1: MAESTRO DE PROVEEDORES
A2: EMPRESA | B2: TIPO | C2: ENCARGADO | D2: CORREO | E2: TELEFONO | F2: COND. PAGO | G2: DETALLE
A3: ACUICOLA ALAS SPA | B3: PESCADOS Y CAVIAR | C3: Felipe Tisné - Viviana Olmos | D3: ventas@kenoz.cl,ftisne@kenoz.cl,contabilidad@acuicolaalas.cl | E3: 56961682811 - 56224766094 | F3: 30 dias
A4: Agricola y Ganadera Santa Laura Spa | B4: CARNES | C4: MARIE HERRERA | D4: mherrera@ganaderasantalaura.cl | F4: 30 dias
A5: ANDES BLEND SPA | B5: VINOS | C5: Johana Guerra | D5: cobranzas@andesblend.cl,johana.guerra@andesblend.cl,rene.ayala@andesblend.cl,pablo.alvarez@andesblend.cl | E5: 569 27314288 - 56983623633 | F5: 30 dias
A6: Bidfood Chile SA | B6: ABARROTES | C6: ARELI | D6: pagos@bidfood.cl,pmolina@bidfood.cl | E6: 56225994444 - 56998038459 | F6: 30 dias | G6: verificar pagina web
A7: CASERITA EN CASA SPA | B7: FRUTAS Y VERDURAS | C7: Francisco Montaner | D7: caseritaencasa@gmail.com | E7: 56952069703 | F7: 30 dias
A8: COM Y DIST DE PRODUCTOS DEL MAR CHRISTIAN OLGUIN | B8: PESCADOS Y MARISCOS | C8: MARCELA UGARTE | D8: mudellarossa@gmail.com | E8: 56965657557 | F8: 30 dias
A9: Comercial Bastien | B9: REPOSTERIA Y PASTELERIA | C9: Paulina Medina | D9: pmedina@bastien.cl,ventas@bastien.cl | E9: 56223307540 | F9: 30 dias
A10: COMERCIAL BIOLACTEOS SPA | B10: CULTIVOS LIOFILIZADO EN POLVO | C10: Gonzalo Ortega | D10: gonzalo@fermentosdelsur.cl | E10: 56979639333 | F10: 30 dias
A11: COMERCIAL BOTE DE PESCA SPA | B11: MARISCOS Y PECADOS | C11: MAX HERRERA | D11: ventas@botedepesca.cl,max@botedepesca.cl,contabilidad@botedepesca.cl,nicolasklima@botedepesca.cl | E11: 56993435700 | F11: 30 dias
A12: Comercial Chau | B12: CARNES | C12: Ximena Marquez | D12: jefecobranza@comercialchau.com, ventas@buenacarne.cl,tesoreria@comercialchau.com,asistentecomercial2@comercialchau.com | E12: 56225853801 | F12: 30 dias
A13: COMERCIAL EDWARDS FINE WINES LTDA | B13: VINOS Y LICORES | C13: Diego Edwards | D13: dedwardj@uc.cl,ventas@efwines.cl | F13: 30 dias
A14: COMERCIAL SANTA CATALINA LTDA | B14: ABARROTES Y VERDURAS | C14: Juan Yañez Vargas | D14: santacatalina3@gmail.com | E14: 56996996469 | F14: 30 dias
A15: Comercial Sur Spa | B15: CONDIMENTOS Y ESPECIES | C15: Sebastian Dib - Maria Dib | D15: sdib@etnia.cl, medib@etnia.cl | E15: 56966473468 | F15: 30 dias
A16: COMERCIAL VALENZUELA COMPANIA LIMITADA | B16: MARISCOS | C16: MILLARAY VALENZUEA | D16: valenzuela.contabilidad@hotmail.com | F16: 30 dias
A17: Comercializador y Dist San Andres y CIA Ltda | B17: ABARROTES | C17: NICOLE LANAS | D17: COBRANZA@CSANANDRES.CL,nicole.lanas@csanandres.cl | E17: (32) 281 4893 | F17: 30 dias
A18: COMERCIALIZADORA AYM LTDA | D18: cecialvear@gmail.com | F18: 30 dias
A19: Comercializadora Benbo Spa | B19: HUEVOS | C19: Nicolas Borobio | D19: equipo@benbo.cl,ventas@benbo.cl | F19: 30 dias
A20: Comercializadora de copihues org Ltda | B20: COPIHUES | C20: JUAN PABLO | D20: plaza.juanpablo@gmail.com | F20: 30 dias
A21: FRUTERIA CENTRAL SPA | B21: FRUTAS Y VERDURAS | C21: GERALDINE ESCOBAR | D21: gescobargalvez@gmail.com | F21: 30 dias
A22: GOURMET SELECT LTDA | B22: ESPECIES | C22: Génesis Sanchez | D22: chef@gourmetselect.cl,contabilidad@gourmetselect.cl,pedidos@gourmetselect.cl,info@gourmetselect.cl | E22: 56944921093 | F22: 30 dias | G22: consultar web
A23: Grupo Dk Servicios Limitada | B23: ASEO | C23: Adriana Salazar - Yilsa Paredes | D23: contacto@grupodk.cl,asistente@grupodk.cl | E23: 56222767775 - 56954202544 - 950058344 | F23: 30 dias
A24: IMPORTADORA Y ALIMENTOS ICB FOOD SERVICE SPA | B24: ABARROTES | C24: ROXANA LUGO | D24: rlugo@icbfs.cl | E24: 56942914322 | F24: 30 dias
A25: La Vinoteca | B25: VINOS Y LICORES | C25: Johana Quiroga - Andrea Aristizabal | D25: andrea.aristizabal@lavinoteca.cl, johanna.quiroga@lavinoteca.cl, margarita.arias@lavinoteca.cl | E25: 56228292221 - 56992197824 | F25: 30 dias
A26: MARALMA FOOD SPA | B26: MARISCOS Y PESCADOS | C26: Felipe Mena - Areangel Gomez | D26: cobranzas@maralmafood.cl,felipemena@maralmafood.cl | E26: 56985044772 | F26: 30 dias
A27: MAURICIO CESAR DIAZ FERNANDEZ | B27: VINOS Y LICORES | C27: MAURICIO DIAZ | D27: licoval@licoval.cl | E27: 56992568880 | F27: 30 dias
A28: MAXIO2 LTDA (oxigeno y nitrogeno) | B28: NITROGENO | C28: JAIME LOPEZ | D28: maxi-o2@outlook.com | E28: 56942263934 | F28: contado
A29: MINIMARKET Y PROCESADORA MAURICIO ALFREDO REYES AROS EIRL | B29: ABARROTES | C29: Karla Vidal Aros | D29: karlaandrea.vidalaros500@gmail.com,mrsabores@gmail.com | E29: 56940685328 | F29: 30 dias
A30: MIRAI RAMEN SPA | B30: ESPORAS | C30: Ismael Poblete | D30: ismael@miraifoodlab.cl,pagos@miraifoodlab.cl | F30: 30 dias
A31: NATURALEZA FEMENINA SPA | B31: ABARROTES | C31: Karla Vidal Aros | D31: karlaandrea.vidalaros500@gmail.com,naturalezafemeninaspa@gmail.com | E31: 56940685328 | F31: 30 dias
A32: PALAIS GOURMET LIMITADA | B32: CARNES Y LACTEOS | C32: Camila Morales - Gonzalo Rivas | D32: grivas@palaisgourmet.cl | E32: 56942132129 | F32: 30 dias
A33: ROSA BUSTOS PARRA SPA | B33: MARISCOS Y PESCADOS | C33: ROSA BUSTOS | D33: rosa.bustos@distemar.cl,distemar.ryn@gmail.com | F33: 30 dias
A34: SOCIEDAD AGRICOLA LOS FAISANES LIMITADA | B34: CARNES EXOTICOS | D34: marcelloavatte@hotmail.com | F34: 30 dias
A35: SOCIEDAD GANADERA RODRIGUEZ Y GRASSI CIA LTDA | B35: CARNES | C35: Patricia Tapia | D35: gr.ganaderareal@gmail.com | E35: 56983670527 | F35: 30 dias
A36: TRUFEROSGRAU SPA | B36: TRUFAS Y HONGOS | C36: MIRENTXU | D36: facturacion@truferosgrau.cl,mruiz@truferosgrau.cl | E36: 56968024411 | F36: 30 dias
A37: NEUCOBER S.A | B37: CHOCOLATE | C37: DANIEL GONZALEZ | D37: danielgonzalez@neucober.cl | E37: 56978895811 | F37: 30 días
A38: Leche Fresca SpA | B38: Leche fresca pasteurizada | C38: LUIS INFANTE | D38: luis@frescarebeca.cl | E38: 56985008017 | F38: 30 días
A39: Agrogourmet | B39: Chocolateria | C39: Carolina Montezuma. | D39: carolina@agourmet.cl | E39: 56990220710 | F39: 30 días
A40: GRV | B40: ASEO | C40: MARITZA DE LA CERDA | D40: MARITZA.DELACERDA@GRV.CL; oscar.soto@grv.cl | E40: 56961247783 | F40: 30 días
A41: Logistic Servis Spa | B41: ABARROTE, ALCOHOLICAS Y ANALCOLICAS | C41: Eduardo Torres | D41: operaciones@logisticfood.cl | E41: 56975445082
A42: Valle del Laja Spa | B42: HONGOS | D42: info@kugar.cl

Sheet CONSOLIDADO PRECIOS
A1: MAESTRO DE PRECIOS POR PROVEEDOR
A2: Factor de incremento: | B2: 0.1
A4: CATEGORÍA | B4: INGREDIENTE | C4: UM | D4: CANT. | E4: PROVEEDOR 1 | F4: TIPO | G4: CORREO | H4: TELÉFONO | I4: PRECIO P1 | J4: PROVEEDOR 2 | K4: TIPO | L4: CORREO | M4: TELÉFONO | N4: PRECIO P2 | O4: PROVEEDOR 3 | P4: TIPO | Q4: CORREO | R4: TELÉFONO | S4: PRECIO P3 | T4: PROMEDIO | U4: PRECIO ESTIMADO
A5: ABARROTE
A6: ABARROTE | B6: ACEITE DE CANOLA | C6: L | D6: 0.02 | E6: Bidfood Chile SA | F6: =IFERROR(VLOOKUP(E6,PROVEEDORES!$A$3:$G$42,2,0),"") -> ABARROTES | G6: =IFERROR(VLOOKUP(E6,PROVEEDORES!$A$3:$G$42,4,0),"") -> pagos@bidfood.cl,pmolina@bidfood.cl | H6: =IFERROR(VLOOKUP(E6,PROVEEDORES!$A$3:$G$42,5,0),"") -> 56225994444 - 56998038459 | I6: 3250 | J6: GOURMET SELECT LTDA | K6: =IFERROR(VLOOKUP(J6,PROVEEDORES!$A$3:$G$42,2,0),"") -> ESPECIES | L6: =IFERROR(VLOOKUP(J6,PROVEEDORES!$A$3:$G$42,4,0),"") -> chef@gourmetselect.cl,contabilidad@gourmetselect.cl,pedidos@gourmetselect.cl,info@gourmetselect.cl | M6: =IFERROR(VLOOKUP(J6,PROVEEDORES!$A$3:$G$42,5,0),"") -> 56944921093 | N6: 3484 | O6: CASERITA EN CASA SPA | P6: =IFERROR(VLOOKUP(O6,PROVEEDORES!$A$3:$G$42,2,0),"") -> FRUTAS Y VERDURAS | Q6: =IFERROR(VLOOKUP(O6,PROVEEDORES!$A$3:$G$42,4,0),"") -> caseritaencasa@gmail.com | R6: =IFERROR(VLOOKUP(O6,PROVEEDORES!$A$3:$G$42,5,0),"") -> 56952069703 | S6: 3043 | T6: =AVERAGE(I6,N6,S6) -> 3259 | U6: =T6*(1+$B$2) -> 3584.9
A7: ABARROTE | B7: ACEITE DE COCO | C7: L | D7: 0.01125 | E7: Bidfood Chile SA | F7: =IFERROR(VLOOKUP(E7,PROVEEDORES!$A$3:$G$42,2,0),"") -> ABARROTES | G7: =IFERROR(VLOOKUP(E7,PROVEEDORES!$A$3:$G$42,4,0),"") -> pagos@bidfood.cl,pmolina@bidfood.cl | H7: =IFERROR(VLOOKUP(E7,PROVEEDORES!$A$3:$G$42,5,0),"") -> 56225994444 - 56998038459 | I7: 10990 | J7: GOURMET SELECT LTDA | K7: =IFERROR(VLOOKUP(J7,PROVEEDORES!$A$3:$G$42,2,0),"") -> ESPECIES | L7: =IFERROR(VLOOKUP(J7,PROVEEDORES!$A$3:$G$42,4,0),"") -> chef@gourmetselect.cl,contabilidad@gourmetselect.cl,pedidos@gourmetselect.cl,info@gourmetselect.cl | M7: =IFERROR(VLOOKUP(J7,PROVEEDORES!$A$3:$G$42,5,0),"") -> 56944921093 | N7: 10281 | O7: CASERITA EN CASA SPA | P7: =IFERROR(VLOOKUP(O7,PROVEEDORES!$A$3:$G$42,2,0),"") -> FRUTAS Y VERDURAS | Q7: =IFERROR(VLOOKUP(O7,PROVEEDORES!$A$3:$G$42,4,0),"") -> caseritaencasa@gmail.com | R7: =IFERROR(VLOOKUP(O7,PROVEEDORES!$A$3:$G$42,5,0),"") -> 56952069703 | S7: 15100 | T7: =AVERAGE(I7,N7,S7) -> 12123.667 | U7: =T7*(1+$B$2) -> 13336.033
A8: ABARROTE | B8: ACEITE DE MAIZ | C8: L | D8: 0.00375 | E8: Bidfood Chile SA | F8: =IFERROR(VLOOKUP(E8,PROVEEDORES!$A$3:$G$42,2,0),"") -> ABARROTES | G8: =IFERROR(VLOOKUP(E8,PROVEEDORES!$A$3:$G$42,4,0),"") -> pagos@bidfood.cl,pmolina@bidfood.cl | H8: =IFERROR(VLOOKUP(E8,PROVEEDORES!$A$3:$G$42,5,0),"") -> 56225994444 - 56998038459 | I8: 4980 | J8: GOURMET SELECT LTDA | K8: =IFERROR(VLOOKUP(J8,PROVEEDORES!$A$3:$G$42,2,0),"") -> ESPECIES | L8: =IFERROR(VLOOKUP(J8,PROVEEDORES!$A$3:$G$42,4,0),"") -> chef@gourmetselect.cl,contabilidad@gourmetselect.cl,pedidos@gourmetselect.cl,info@gourmetselect.cl | M8: =IFERROR(VLOOKUP(J8,PROVEEDORES!$A$3:$G$42,5,0),"") -> 56944921093 | N8: 5316 | O8: CASERITA EN CASA SPA | P8: =IFERROR(VLOOKUP(O8,PROVEEDORES!$A$3:$G$42,2,0),"") -> FRUTAS Y VERDURAS | Q8: =IFERROR(VLOOKUP(O8,PROVEEDORES!$A$3:$G$42,4,0),"") -> caseritaencasa@gmail.com | R8: =IFERROR(VLOOKUP(O8,PROVEEDORES!$A$3:$G$42,5,0),"") -> 56952069703 | S8: 7763 | T8: =AVERAGE(I8,N8,S8) -> 6019.6667 | U8: =T8*(1+$B$2) -> 6621.6333
A9: ABARROTE | B9: ACEITE DE MARAVILLA | C9: L | D9: 1.756625 | E9: Bidfood Chile SA | F9: =IFERROR(VLOOKUP(E9,PROVEEDORES!$A$3:$G$42,2,0),"") -> ABARROTES | G9: =IFERROR(VLOOKUP(E9,PROVEEDORES!$A$3:$G$42,4,0),"") -> pagos@bidfood.cl,pmolina@bidfood.cl | H9: =IFERROR(VLOOKUP(E9,PROVEEDORES!$A$3:$G$42,5,0),"") -> 56225994444 - 56998038459 | I9: 2304 | J9: GOURMET SELECT LTDA | K9: =IFERROR(VLOOKUP(J9,PROVEEDORES!$A$3:$G$42,2,0),"") -> ESPECIES | L9: =IFERROR(VLOOKUP(J9,PROVEEDORES!$A$3:$G$42,4,0),"") -> chef@gourmetselect.cl,contabilidad@gourmetselect.cl,pedidos@gourmetselect.cl,info@gourmetselect.cl | M9: =IFERROR(VLOOKUP(J9,PROVEEDORES!$A$3:$G$42,5,0),"") -> 56944921093 | N9: 3448 | O9: CASERITA EN CASA SPA | P9: =IFERROR(VLOOKUP(O9,PROVEEDORES!$A$3:$G$42,2,0),"") -> FRUTAS Y VERDURAS | Q9: =IFERROR(VLOOKUP(O9,PROVEEDORES!$A$3:$G$42,4,0),"") -> caseritaencasa@gmail.com | R9: =IFERROR(VLOOKUP(O9,PROVEEDORES!$A$3:$G$42,5,0),"") -> 56952069703 | S9: 3850 | T9: =AVERAGE(I9,N9,S9) -> 3200.6667 | U9: =T9*(1+$B$2) -> 3520.7333
A10: ABARROTE | B10: ACEITE DE OLIVA | C10: L | D10: 1.0346875 | E10: Bidfood Chile SA | F10: =IFERROR(VLOOKUP(E10,PROVEEDORES!$A$3:$G$42,2,0),"") -> ABARROTES | G10: =IFERROR(VLOOKUP(E10,PROVEEDORES!$A$3:$G$42,4,0),"") -> pagos@bidfood.cl,pmolina@bidfood.cl | H10: =IFERROR(VLOOKUP(E10,PROVEEDORES!$A$3:$G$42,5,0),"") -> 56225994444 - 56998038459 | I10: 14516 | J10: GOURMET SELECT LTDA | K10: =IFERROR(VLOOKUP(J10,PROVEEDORES!$A$3:$G$42,2,0),"") -> ESPECIES | L10: =IFERROR(VLOOKUP(J10,PROVEEDORES!$A$3:$G$42,4,0),"") -> chef@gourmetselect.cl,contabilidad@gourmetselect.cl,pedidos@gourmetselect.cl,info@gourmetselect.cl | M10: =IFERROR(VLOOKUP(J10,PROVEEDORES!$A$3:$G$42,5,0),"") -> 56944921093 | N10: 18087 | O10: CASERITA EN CASA SPA | P10: =IFERROR(VLOOKUP(O10,PROVEEDORES!$A$3:$G$42,2,0),"") -> FRUTAS Y VERDURAS | Q10: =IFERROR(VLOOKUP(O10,PROVEEDORES!$A$3:$G$42,4,0),"") -> caseritaencasa@gmail.com | R10: =IFERROR(VLOOKUP(O10,PROVEEDORES!$A$3:$G$42,5,0),"") -> 56952069703 | S10: 15378 | T10: =AVERAGE(I10,N10,S10) -> 15993.667 | U10: =T10*(1+$B$2) -> 17593.033
A11: ABARROTE | B11: ACEITE DE SESAMO | C11: L | D11: 0.015625 | E11: Bidfood Chile SA | F11: =IFERROR(VLOOKUP(E11,PROVEEDORES!$A$3:$G$42,2,0),"") -> ABARROTES | G11: =IFERROR(VLOOKUP(E11,PROVEEDORES!$A$3:$G$42,4,0),"") -> pagos@bidfood.cl,pmolina@bidfood.cl | H11: =IFERROR(VLOOKUP(E11,PROVEEDORES!$A$3:$G$42,5,0),"") -> 56225994444 - 56998038459 | I11: 11872 | J11: GOURMET SELECT LTDA | K11: =IFERROR(VLOOKUP(J11,PROVEEDORES!$A$3:$G$42,2,0),"") -> ESPECIES | L11: =IFERROR(VLOOKUP(J11,PROVEEDORES!$A$3:$G$42,4,0),"") -> chef@gourmetselect.cl,contabilidad@gourmetselect.cl,pedidos@gourmetselect.cl,info@gourmetselect.cl | M11: =IFERROR(VLOOKUP(J11,PROVEEDORES!$A$3:$G$42,5,0),"") -> 56944921093 | N11: 16039 | O11: CASERITA EN CASA SPA | P11: =IFERROR(VLOOKUP(O11,PROVEEDORES!$A$3:$G$42,2,0),"") -> FRUTAS Y VERDURAS | Q11: =IFERROR(VLOOKUP(O11,PROVEEDORES!$A$3:$G$42,4,0),"") -> caseritaencasa@gmail.com | R11: =IFERROR(VLOOKUP(O11,PROVEEDORES!$A$3:$G$42,5,0),"") -> 56952069703 | S11: 1111 | T11: =AVERAGE(I11,N11,S11) -> 9674 | U11: =T11*(1+$B$2) -> 10641.4
A12: ABARROTE | B12: ACEITE PARA FREIR | C12: L | D12: 4.45 | E12: Bidfood Chile SA | F12: =IFERROR(VLOOKUP(E12,PROVEEDORES!$A$3:$G$42,2,0),"") -> ABARROTES | G12: =IFERROR(VLOOKUP(E12,PROVEEDORES!$A$3:$G$42,4,0),"") -> pagos@bidfood.cl,pmolina@bidfood.cl | H12: =IFERROR(VLOOKUP(E12,PROVEEDORES!$A$3:$G$42,5,0),"") -> 56225994444 - 56998038459 | I12: 2270 | J12: GOURMET SELECT LTDA | K12: =IFERROR(VLOOKUP(J12,PROVEEDORES!$A$3:$G$42,2,0),"") -> ESPECIES | L12: =IFERROR(VLOOKUP(J12,PROVEEDORES!$A$3:$G$42,4,0),"") -> chef@gourmetselect.cl,contabilidad@gourmetselect.cl,pedidos@gourmetselect.cl,info@gourmetselect.cl | M12: =IFERROR(VLOOKUP(J12,PROVEEDORES!$A$3:$G$42,5,0),"") -> 56944921093 | N12: 2832 | O12: CASERITA EN CASA SPA | P12: =IFERROR(VLOOKUP(O12,PROVEEDORES!$A$3:$G$42,2,0),"") -> FRUTAS Y VERDURAS | Q12: =IFERROR(VLOOKUP(O12,PROVEEDORES!$A$3:$G$42,4,0),"") -> caseritaencasa@gmail.com | R12: =IFERROR(VLOOKUP(O12,PROVEEDORES!$A$3:$G$42,5,0),"") -> 56952069703 | S12: 927 | T12: =AVERAGE(I12,N12,S12) -> 2009.6667 | U12: =T12*(1+$B$2) -> 2210.6333
A13: ABARROTE | B13: ACEITE SEMILLA DE GIRASOL | C13: L | D13: 0.1725 | E13: Bidfood Chile SA | F13: =IFERROR(VLOOKUP(E13,PROVEEDORES!$A$3:$G$42,2,0),"") -> ABARROTES | G13: =IFERROR(VLOOKUP(E13,PROVEEDORES!$A$3:$G$42,4,0),"") -> pagos@bidfood.cl,pmolina@bidfood.cl | H13: =IFERROR(VLOOKUP(E13,PROVEEDORES!$A$3:$G$42,5,0),"") -> 56225994444 - 56998038459 | I13: 3878 | J13: GOURMET SELECT LTDA | K13: =IFERROR(VLOOKUP(J13,PROVEEDORES!$A$3:$G$42,2,0),"") -> ESPECIES | L13: =IFERROR(VLOOKUP(J13,PROVEEDORES!$A$3:$G$42,4,0),"") -> chef@gourmetselect.cl,contabilidad@gourmetselect.cl,pedidos@gourmetselect.cl,info@gourmetselect.cl | M13: =IFERROR(VLOOKUP(J13,PROVEEDORES!$A$3:$G$42,5,0),"") -> 56944921093 | N13: 1045 | O13: CASERITA EN CASA SPA | P13: =IFERROR(VLOOKUP(O13,PROVEEDORES!$A$3:$G$42,2,0),"") -> FRUTAS Y VERDURAS | Q13: =IFERROR(VLOOKUP(O13,PROVEEDORES!$A$3:$G$42,4,0),"") -> caseritaencasa@gmail.com | R13: =IFERROR(VLOOKUP(O13,PROVEEDORES!$A$3:$G$42,5,0),"") -> 56952069703 | S13: 2914 | T13: =AVERAGE(I13,N13,S13) -> 2612.3333 | U13: =T13*(1+$B$2) -> 2873.5667
A14: ABARROTE | B14: ACEITE VEGETAL | C14: L | D14: 1.87825 | E14: Bidfood Chile SA | F14: =IFERROR(VLOOKUP(E14,PROVEEDORES!$A$3:$G$42,2,0),"") -> ABARROTES | G14: =IFERROR(VLOOKUP(E14,PROVEEDORES!$A$3:$G$42,4,0),"") -> pagos@bidfood.cl,pmolina@bidfood.cl | H14: =IFERROR(VLOOKUP(E14,PROVEEDORES!$A$3:$G$42,5,0),"") -> 56225994444 - 56998038459 | I14: 2300 | J14: GOURMET SELECT LTDA | K14: =IFERROR(VLOOKUP(J14,PROVEEDORES!$A$3:$G$42,2,0),"") -> ESPECIES | L14: =IFERROR(VLOOKUP(J14,PROVEEDORES!$A$3:$G$42,4,0),"") -> chef@gourmetselect.cl,contabilidad@gourmetselect.cl,pedidos@gourmetselect.cl,info@gourmetselect.cl | M14: =IFERROR(VLOOKUP(J14,PROVEEDORES!$A$3:$G$42,5,0),"") -> 56944921093 | N14: 3014 | O14: CASERITA EN CASA SPA | P14: =IFERROR(VLOOKUP(O14,PROVEEDORES!$A$3:$G$42,2,0),"") -> FRUTAS Y VERDURAS | Q14: =IFERROR(VLOOKUP(O14,PROVEEDORES!$A$3:$G$42,4,0),"") -> caseritaencasa@gmail.com | R14: =IFERROR(VLOOKUP(O14,PROVEEDORES!$A$3:$G$42,5,0),"") -> 56952069703 | S14: 838 | T14: =AVERAGE(I14,N14,S14) -> 2050.6667 | U14: =T14*(1+$B$2) -> 2255.7333
A15: ABARROTE | B15: ACEITUNAS MORADAS | C15: kg | D15: 0.015625 | E15: Bidfood Chile SA | F15: =IFERROR(VLOOKUP(E15,PROVEEDORES!$A$3:$G$42,2,0),"") -> ABARROTES | G15: =IFERROR(VLOOKUP(E15,PROVEEDORES!$A$3:$G$42,4,0),"") -> pagos@bidfood.cl,pmolina@bidfood.cl | H15: =IFERROR(VLOOKUP(E15,PROVEEDORES!$A$3:$G$42,5,0),"") -> 56225994444 - 56998038459 | I15: 8194 | J15: GOURMET SELECT LTDA | K15: =IFERROR(VLOOKUP(J15,PROVEEDORES!$A$3:$G$42,2,0),"") -> ESPECIES | L15: =IFERROR(VLOOKUP(J15,PROVEEDORES!$A$3:$G$42,4,0),"") -> chef@gourmetselect.cl,contabilidad@gourmetselect.cl,pedidos@gourmetselect.cl,info@gourmetselect.cl | M15: =IFERROR(VLOOKUP(J15,PROVEEDORES!$A$3:$G$42,5,0),"") -> 56944921093 | N15: 5048 | O15: CASERITA EN CASA SPA | P15: =IFERROR(VLOOKUP(O15,PROVEEDORES!$A$3:$G$42,2,0),"") -> FRUTAS Y VERDURAS | Q15: =IFERROR(VLOOKUP(O15,PROVEEDORES!$A$3:$G$42,4,0),"") -> caseritaencasa@gmail.com | R15: =IFERROR(VLOOKUP(O15,PROVEEDORES!$A$3:$G$42,5,0),"") -> 56952069703 | S15: 5292 | T15: =AVERAGE(I15,N15,S15) -> 6178 | U15: =T15*(1+$B$2) -> 6795.8
A16: ABARROTE | B16: ACEITUNAS NEGRAS C/HUESO | C16: kg | D16: 0.009375 | E16: Bidfood Chile SA | F16: =IFERROR(VLOOKUP(E16,PROVEEDORES!$A$3:$G$42,2,0),"") -> ABARROTES | G16: =IFERROR(VLOOKUP(E16,PROVEEDORES!$A$3:$G$42,4,0),"") -> pagos@bidfood.cl,pmolina@bidfood.cl | H16: =IFERROR(VLOOKUP(E16,PROVEEDORES!$A$3:$G$42,5,0),"") -> 56225994444 - 56998038459 | I16: 4522 | J16: GOURMET SELECT LTDA | K16: =IFERROR(VLOOKUP(J16,PROVEEDORES!$A$3:$G$42,2,0),"") -> ESPECIES | L16: =IFERROR(VLOOKUP(J16,PROVEEDORES!$A$3:$G$42,4,0),"") -> chef@gourmetselect.cl,contabilidad@gourmetselect.cl,pedidos@gourmetselect.cl,info@gourmetselect.cl | M16: =IFERROR(VLOOKUP(J16,PROVEEDORES!$A$3:$G$42,5,0),"") -> 56944921093 | N16: 2860 | O16: CASERITA EN CASA SPA | P16: =IFERROR(VLOOKUP(O16,PROVEEDORES!$A$3:$G$42,2,0),"") -> FRUTAS Y VERDURAS | Q16: =IFERROR(VLOOKUP(O16,PROVEEDORES!$A$3:$G$42,4,0),"") -> caseritaencasa@gmail.com | R16: =IFERROR(VLOOKUP(O16,PROVEEDORES!$A$3:$G$42,5,0),"") -> 56952069703 | S16: 2343 | T16: =AVERAGE(I16,N16,S16) -> 3241.6667 | U16: =T16*(1+$B$2) -> 3565.8333
A17: ABARROTE | B17: ACEITUNAS NEGRAS S/HUESO | C17: kg | D17: 0.2075 | E17: Bidfood Chile SA | F17: =IFERROR(VLOOKUP(E17,PROVEEDORES!$A$3:$G$42,2,0),"") -> ABARROTES | G17: =IFERROR(VLOOKUP(E17,PROVEEDORES!$A$3:$G$42,4,0),"") -> pagos@bidfood.cl,pmolina@bidfood.cl | H17: =IFERROR(VLOOKUP(E17,PROVEEDORES!$A$3:$G$42,5,0),"") -> 56225994444 - 56998038459 | I17: 5562 | J17: GOURMET SELECT LTDA | K17: =IFERROR(VLOOKUP(J17,PROVEEDORES!$A$3:$G$42,2,0),"") -> ESPECIES | L17: =IFERROR(VLOOKUP(J17,PROVEEDORES!$A$3:$G$42,4,0),"") -> chef@gourmetselect.cl,contabilidad@gourmetselect.cl,pedidos@gourmetselect.cl,info@gourmetselect.cl | M17: =IFERROR(VLOOKUP(J17,PROVEEDORES!$A$3:$G$42,5,0),"") -> 56944921093 | N17: 4511 | O17: CASERITA EN CASA SPA | P17: =IFERROR(VLOOKUP(O17,PROVEEDORES!$A$3:$G$42,2,0),"") -> FRUTAS Y VERDURAS | Q17: =IFERROR(VLOOKUP(O17,PROVEEDORES!$A$3:$G$42,4,0),"") -> caseritaencasa@gmail.com | R17: =IFERROR(VLOOKUP(O17,PROVEEDORES!$A$3:$G$42,5,0),"") -> 56952069703 | S17: 3372 | T17: =AVERAGE(I17,N17,S17) -> 4481.6667 | U17: =T17*(1+$B$2) -> 4929.8333
... A244: ABARROTE | B244: YUZU EN PASTA | C244: kg | D244: 0.003625 | E244: Bidfood Chile SA | F244: =IFERROR(VLOOKUP(E244,PROVEEDORES!$A$3:$G$42,2,0),"") -> ABARROTES | G244: =IFERROR(VLOOKUP(E244,PROVEEDORES!$A$3:$G$42,4,0),"") -> pagos@bidfood.cl,pmolina@bidfood.cl | H244: =IFERROR(VLOOKUP(E244,PROVEEDORES!$A$3:$G$42,5,0),"") -> 56225994444 - 56998038459 | I244: 27270 | J244: GOURMET SELECT LTDA | K244: =IFERROR(VLOOKUP(J244,PROVEEDORES!$A$3:$G$42,2,0),"") -> ESPECIES | L244: =IFERROR(VLOOKUP(J244,PROVEEDORES!$A$3:$G$42,4,0),"") -> chef@gourmetselect.cl,contabilidad@gourmetselect.cl,pedidos@gourmetselect.cl,info@gourmetselect.cl | M244: =IFERROR(VLOOKUP(J244,PROVEEDORES!$A$3:$G$42,5,0),"") -> 56944921093 | N244: 12544 | O244: CASERITA EN CASA SPA | P244: =IFERROR(VLOOKUP(O244,PROVEEDORES!$A$3:$G$42,2,0),"") -> FRUTAS Y VERDURAS | Q244: =IFERROR(VLOOKUP(O244,PROVEEDORES!$A$3:$G$42,4,0),"") -> caseritaencasa@gmail.com | R244: =IFERROR(VLOOKUP(O244,PROVEEDORES!$A$3:$G$42,5,0),"") -> 56952069703 | S244: 18571 | T244: =AVERAGE(I244,N244,S244) -> 19461.667 | U244: =T244*(1+$B$2) -> 21407.833
A245: AGUA
A246: AGUA | B246: AGUA DE ROSAS | C246: L | D246: 0.0025 | E246: Bidfood Chile SA | F246: =IFERROR(VLOOKUP(E246,PROVEEDORES!$A$3:$G$42,2,0),"") -> ABARROTES | G246: =IFERROR(VLOOKUP(E246,PROVEEDORES!$A$3:$G$42,4,0),"") -> pagos@bidfood.cl,pmolina@bidfood.cl | H246: =IFERROR(VLOOKUP(E246,PROVEEDORES!$A$3:$G$42,5,0),"") -> 56225994444 - 56998038459 | I246: 13919 | J246: GOURMET SELECT LTDA | K246: =IFERROR(VLOOKUP(J246,PROVEEDORES!$A$3:$G$42,2,0),"") -> ESPECIES | L246: =IFERROR(VLOOKUP(J246,PROVEEDORES!$A$3:$G$42,4,0),"") -> chef@gourmetselect.cl,contabilidad@gourmetselect.cl,pedidos@gourmetselect.cl,info@gourmetselect.cl | M246: =IFERROR(VLOOKUP(J246,PROVEEDORES!$A$3:$G$42,5,0),"") -> 56944921093 | N246: 12750 | T246: =AVERAGE(I246,N246) -> 13334.5 | U246: =T246*(1+$B$2) -> 14667.95
A247: AGUA | B247: AGUA MINERAL C/GAS | C247: L | D247: 0.05 | E247: Bidfood Chile SA | F247: =IFERROR(VLOOKUP(E247,PROVEEDORES!$A$3:$G$42,2,0),"") -> ABARROTES | G247: =IFERROR(VLOOKUP(E247,PROVEEDORES!$A$3:$G$42,4,0),"") -> pagos@bidfood.cl,pmolina@bidfood.cl | H247: =IFERROR(VLOOKUP(E247,PROVEEDORES!$A$3:$G$42,5,0),"") -> 56225994444 - 56998038459 | I247: 956 | J247: GOURMET SELECT LTDA | K247: =IFERROR(VLOOKUP(J247,PROVEEDORES!$A$3:$G$42,2,0),"") -> ESPECIES | L247: =IFERROR(VLOOKUP(J247,PROVEEDORES!$A$3:$G$42,4,0),"") -> chef@gourmetselect.cl,contabilidad@gourmetselect.cl,pedidos@gourmetselect.cl,info@gourmetselect.cl | M247: =IFERROR(VLOOKUP(J247,PROVEEDORES!$A$3:$G$42,5,0),"") -> 56944921093 | N247: 255 | T247: =AVERAGE(I247,N247) -> 605.5 | U247: =T247*(1+$B$2) -> 666.05
A248: ALGAS
A249: ALGAS | B249: LUCHE | C249: kg | D249: 0.00375 | E249: Bidfood Chile SA | F249: =IFERROR(VLOOKUP(E249,PROVEEDORES!$A$3:$G$42,2,0),"") -> ABARROTES | G249: =IFERROR(VLOOKUP(E249,PROVEEDORES!$A$3:$G$42,4,0),"") -> pagos@bidfood.cl,pmolina@bidfood.cl | H249: =IFERROR(VLOOKUP(E249,PROVEEDORES!$A$3:$G$42,5,0),"") -> 56225994444 - 56998038459 | I249: 14280 | J249: GOURMET SELECT LTDA | K249: =IFERROR(VLOOKUP(J249,PROVEEDORES!$A$3:$G$42,2,0),"") -> ESPECIES | L249: =IFERROR(VLOOKUP(J249,PROVEEDORES!$A$3:$G$42,4,0),"") -> chef@gourmetselect.cl,contabilidad@gourmetselect.cl,pedidos@gourmetselect.cl,info@gourmetselect.cl | M249: =IFERROR(VLOOKUP(J249,PROVEEDORES!$A$3:$G$42,5,0),"") -> 56944921093 | N249: 7126 | O249: CASERITA EN CASA SPA | P249: =IFERROR(VLOOKUP(O249,PROVEEDORES!$A$3:$G$42,2,0),"") -> FRUTAS Y VERDURAS | Q249: =IFERROR(VLOOKUP(O249,PROVEEDORES!$A$3:$G$42,4,0),"") -> caseritaencasa@gmail.com | R249: =IFERROR(VLOOKUP(O249,PROVEEDORES!$A$3:$G$42,5,0),"") -> 56952069703 | S249: 5389 | T249: =AVERAGE(I249,N249,S249) -> 8931.6667 | U249: =T249*(1+$B$2) -> 9824.8333
A250: ARTICULO COCINA
A251: ARTICULO COCINA | B251: ASTILLAS PARA AHUMAR | C251: kg | D251: 0.04375 | E251: Bidfood Chile SA | F251: =IFERROR(VLOOKUP(E251,PROVEEDORES!$A$3:$G$42,2,0),"") -> ABARROTES | G251: =IFERROR(VLOOKUP(E251,PROVEEDORES!$A$3:$G$42,4,0),"") -> pagos@bidfood.cl,pmolina@bidfood.cl | H251: =IFERROR(VLOOKUP(E251,PROVEEDORES!$A$3:$G$42,5,0),"") -> 56225994444 - 56998038459 | I251: 10000 | J251: GOURMET SELECT LTDA | K251: =IFERROR(VLOOKUP(J251,PROVEEDORES!$A$3:$G$42,2,0),"") -> ESPECIES | L251: =IFERROR(VLOOKUP(J251,PROVEEDORES!$A$3:$G$42,4,0),"") -> chef@gourmetselect.cl,contabilidad@gourmetselect.cl,pedidos@gourmetselect.cl,info@gourmetselect.cl | M251: =IFERROR(VLOOKUP(J251,PROVEEDORES!$A$3:$G$42,5,0),"") -> 56944921093 | N251: 8200 | O251: CASERITA EN CASA SPA | P251: =IFERROR(VLOOKUP(O251,PROVEEDORES!$A$3:$G$42,2,0),"") -> FRUTAS Y VERDURAS | Q251: =IFERROR(VLOOKUP(O251,PROVEEDORES!$A$3:$G$42,4,0),"") -> caseritaencasa@gmail.com | R251: =IFERROR(VLOOKUP(O251,PROVEEDORES!$A$3:$G$42,5,0),"") -> 56952069703 | S251: 13058 | T251: =AVERAGE(I251,N251,S251) -> 10419.333 | U251: =T251*(1+$B$2) -> 11461.267
A252: ARTICULO COCINA | B252: BASE CARTON TORTA 22 CM | C252: UN | D252: 3 | E252: Bidfood Chile SA | F252: =IFERROR(VLOOKUP(E252,PROVEEDORES!$A$3:$G$42,2,0),"") -> ABARROTES | G252: =IFERROR(VLOOKUP(E252,PROVEEDORES!$A$3:$G$42,4,0),"") -> pagos@bidfood.cl,pmolina@bidfood.cl | H252: =IFERROR(VLOOKUP(E252,PROVEEDORES!$A$3:$G$42,5,0),"") -> 56225994444 - 56998038459 | I252: 150 | J252: GOURMET SELECT LTDA | K252: =IFERROR(VLOOKUP(J252,PROVEEDORES!$A$3:$G$42,2,0),"") -> ESPECIES | L252: =IFERROR(VLOOKUP(J252,PROVEEDORES!$A$3:$G$42,4,0),"") -> chef@gourmetselect.cl,contabilidad@gourmetselect.cl,pedidos@gourmetselect.cl,info@gourmetselect.cl | M252: =IFERROR(VLOOKUP(J252,PROVEEDORES!$A$3:$G$42,5,0),"") -> 56944921093 | N252: 200 | O252: CASERITA EN CASA SPA | P252: =IFERROR(VLOOKUP(O252,PROVEEDORES!$A$3:$G$42,2,0),"") -> FRUTAS Y VERDURAS | Q252: =IFERROR(VLOOKUP(O252,PROVEEDORES!$A$3:$G$42,4,0),"") -> caseritaencasa@gmail.com | R252: =IFERROR(VLOOKUP(O252,PROVEEDORES!$A$3:$G$42,5,0),"") -> 56952069703 | S252: 185 | T252: =AVERAGE(I252,N252,S252) -> 178.33333 | U252: =T252*(1+$B$2) -> 196.16667
A253: ARTICULO COCINA | B253: BLONDA 22 CM | C253: UN | D253: 4 | E253: Bidfood Chile SA | F253: =IFERROR(VLOOKUP(E253,PROVEEDORES!$A$3:$G$42,2,0),"") -> ABARROTES | G253: =IFERROR(VLOOKUP(E253,PROVEEDORES!$A$3:$G$42,4,0),"") -> pagos@bidfood.cl,pmolina@bidfood.cl | H253: =IFERROR(VLOOKUP(E253,PROVEEDORES!$A$3:$G$42,5,0),"") -> 56225994444 - 56998038459 | I253: 300 | J253: GOURMET SELECT LTDA | K253: =IFERROR(VLOOKUP(J253,PROVEEDORES!$A$3:$G$42,2,0),"") -> ESPECIES | L253: =IFERROR(VLOOKUP(J253,PROVEEDORES!$A$3:$G$42,4,0),"") -> chef@gourmetselect.cl,contabilidad@gourmetselect.cl,pedidos@gourmetselect.cl,info@gourmetselect.cl | M253: =IFERROR(VLOOKUP(J253,PROVEEDORES!$A$3:$G$42,5,0),"") -> 56944921093 | N253: 415 | O253: CASERITA EN CASA SPA | P253: =IFERROR(VLOOKUP(O253,PROVEEDORES!$A$3:$G$42,2,0),"") -> FRUTAS Y VERDURAS | Q253: =IFERROR(VLOOKUP(O253,PROVEEDORES!$A$3:$G$42,4,0),"") -> caseritaencasa@gmail.com | R253: =IFERROR(VLOOKUP(O253,PROVEEDORES!$A$3:$G$42,5,0),"") -> 56952069703 | S253: 66 | T253: =AVERAGE(I253,N253,S253) -> 260.33333 | U253: =T253*(1+$B$2) -> 286.36667
A254: ARTICULO COCINA | B254: BOLSA PARA SELLADO AL VACIO 25X35 CM | C254: UN | D254: 2.75 | E254: Bidfood Chile SA | F254: =IFERROR(VLOOKUP(E254,PROVEEDORES!$A$3:$G$42,2,0),"") -> ABARROTES | G254: =IFERROR(VLOOKUP(E254,PROVEEDORES!$A$3:$G$42,4,0),"") -> pagos@bidfood.cl,pmolina@bidfood.cl | H254: =IFERROR(VLOOKUP(E254,PROVEEDORES!$A$3:$G$42,5,0),"") -> 56225994444 - 56998038459 | I254: 108 | J254: GOURMET SELECT LTDA | K254: =IFERROR(VLOOKUP(J254,PROVEEDORES!$A$3:$G$42,2,0),"") -> ESPECIES | L254: =IFERROR(VLOOKUP(J254,PROVEEDORES!$A$3:$G$42,4,0),"") -> chef@gourmetselect.cl,contabilidad@gourmetselect.cl,pedidos@gourmetselect.cl,info@gourmetselect.cl | M254: =IFERROR(VLOOKUP(J254,PROVEEDORES!$A$3:$G$42,5,0),"") -> 56944921093 | N254: 113 | O254: CASERITA EN CASA SPA | P254: =IFERROR(VLOOKUP(O254,PROVEEDORES!$A$3:$G$42,2,0),"") -> FRUTAS Y VERDURAS | Q254: =IFERROR(VLOOKUP(O254,PROVEEDORES!$A$3:$G$42,4,0),"") -> caseritaencasa@gmail.com | R254: =IFERROR(VLOOKUP(O254,PROVEEDORES!$A$3:$G$42,5,0),"") -> 56952069703 | S254: 199 | T254: =AVERAGE(I254,N254,S254) -> 140 | U254: =T254*(1+$B$2) -> 154
A255: ARTICULO COCINA | B255: BOLSA PARA SELLADO AL VACIO 30X40 CM | C255: UN | D255: 0.875 | E255: Bidfood Chile SA | F255: =IFERROR(VLOOKUP(E255,PROVEEDORES!$A$3:$G$42,2,0),"") -> ABARROTES | G255: =IFERROR(VLOOKUP(E255,PROVEEDORES!$A$3:$G$42,4,0),"") -> pagos@bidfood.cl,pmolina@bidfood.cl | H255: =IFERROR(VLOOKUP(E255,PROVEEDORES!$A$3:$G$42,5,0),"") -> 56225994444 - 56998038459 | I255: 150 | J255: GOURMET SELECT LTDA | K255: =IFERROR(VLOOKUP(J255,PROVEEDORES!$A$3:$G$42,2,0),"") -> ESPECIES | L255: =IFERROR(VLOOKUP(J255,PROVEEDORES!$A$3:$G$42,4,0),"") -> chef@gourmetselect.cl,contabilidad@gourmetselect.cl,pedidos@gourmetselect.cl,info@gourmetselect.cl | M255: =IFERROR(VLOOKUP(J255,PROVEEDORES!$A$3:$G$42,5,0),"") -> 56944921093 | N255: 74 | O255: CASERITA EN CASA SPA | P255: =IFERROR(VLOOKUP(O255,PROVEEDORES!$A$3:$G$42,2,0),"") -> FRUTAS Y VERDURAS | Q255: =IFERROR(VLOOKUP(O255,PROVEEDORES!$A$3:$G$42,4,0),"") -> caseritaencasa@gmail.com | R255: =IFERROR(VLOOKUP(O255,PROVEEDORES!$A$3:$G$42,5,0),"") -> 56952069703 | S255: 34 | T255: =AVERAGE(I255,N255,S255) -> 86 | U255: =T255*(1+$B$2) -> 94.6
A256: ARTICULO COCINA | B256: BOLSA PREPICADA 20 X 30 | C256: UN | D256: 4 | E256: Bidfood Chile SA | F256: =IFERROR(VLOOKUP(E256,PROVEEDORES!$A$3:$G$42,2,0),"") -> ABARROTES | G256: =IFERROR(VLOOKUP(E256,PROVEEDORES!$A$3:$G$42,4,0),"") -> pagos@bidfood.cl,pmolina@bidfood.cl | H256: =IFERROR(VLOOKUP(E256,PROVEEDORES!$A$3:$G$42,5,0),"") -> 56225994444 - 56998038459 | I256: 60 | J256: GOURMET SELECT LTDA | K256: =IFERROR(VLOOKUP(J256,PROVEEDORES!$A$3:$G$42,2,0),"") -> ESPECIES | L256: =IFERROR(VLOOKUP(J256,PROVEEDORES!$A$3:$G$42,4,0),"") -> chef@gourmetselect.cl,contabilidad@gourmetselect.cl,pedidos@gourmetselect.cl,info@gourmetselect.cl | M256: =IFERROR(VLOOKUP(J256,PROVEEDORES!$A$3:$G$42,5,0),"") -> 56944921093 | N256: 101 | O256: CASERITA EN CASA SPA | P256: =IFERROR(VLOOKUP(O256,PROVEEDORES!$A$3:$G$42,2,0),"") -> FRUTAS Y VERDURAS | Q256: =IFERROR(VLOOKUP(O256,PROVEEDORES!$A$3:$G$42,4,0),"") -> caseritaencasa@gmail.com | R256: =IFERROR(VLOOKUP(O256,PROVEEDORES!$A$3:$G$42,5,0),"") -> 56952069703 | S256: 17 | T256: =AVERAGE(I256,N256,S256) -> 59.333333 | U256: =T256*(1+$B$2) -> 65.266667
A257: ARTICULO COCINA | B257: BROCHETA DE BAMBU 10 CM 100 UNI | C257: UN | D257: 0.1 | E257: Bidfood Chile SA | F257: =IFERROR(VLOOKUP(E257,PROVEEDORES!$A$3:$G$42,2,0),"") -> ABARROTES | G257: =IFERROR(VLOOKUP(E257,PROVEEDORES!$A$3:$G$42,4,0),"") -> pagos@bidfood.cl,pmolina@bidfood.cl | H257: =IFERROR(VLOOKUP(E257,PROVEEDORES!$A$3:$G$42,5,0),"") -> 56225994444 - 56998038459 | I257: 590 | J257: GOURMET SELECT LTDA | K257: =IFERROR(VLOOKUP(J257,PROVEEDORES!$A$3:$G$42,2,0),"") -> ESPECIES | L257: =IFERROR(VLOOKUP(J257,PROVEEDORES!$A$3:$G$42,4,0),"") -> chef@gourmetselect.cl,contabilidad@gourmetselect.cl,pedidos@gourmetselect.cl,info@gourmetselect.cl | M257: =IFERROR(VLOOKUP(J257,PROVEEDORES!$A$3:$G$42,5,0),"") -> 56944921093 | N257: 199 | O257: CASERITA EN CASA SPA | P257: =IFERROR(VLOOKUP(O257,PROVEEDORES!$A$3:$G$42,2,0),"") -> FRUTAS Y VERDURAS | Q257: =IFERROR(VLOOKUP(O257,PROVEEDORES!$A$3:$G$42,4,0),"") -> caseritaencasa@gmail.com | R257: =IFERROR(VLOOKUP(O257,PROVEEDORES!$A$3:$G$42,5,0),"") -> 56952069703 | S257: 1004 | T257: =AVERAGE(I257,N257,S257) -> 597.66667 | U257: =T257*(1+$B$2) -> 657.43333
A258: ARTICULO COCINA | B258: BROCHETA DE BAMBU 12 CM 100 UN | C258: UN | D258: 0.226 | E258: Bidfood Chile SA | F258: =IFERROR(VLOOKUP(E258,PROVEEDORES!$A$3:$G$42,2,0),"") -> ABARROTES | G258: =IFERROR(VLOOKUP(E258,PROVEEDORES!$A$3:$G$42,4,0),"") -> pagos@bidfood.cl,pmolina@bidfood.cl | H258: =IFERROR(VLOOKUP(E258,PROVEEDORES!$A$3:$G$42,5,0),"") -> 56225994444 - 56998038459 | I258: 601 | J258: GOURMET SELECT LTDA | K258: =IFERROR(VLOOKUP(J258,PROVEEDORES!$A$3:$G$42,2,0),"") -> ESPECIES | L258: =IFERROR(VLOOKUP(J258,PROVEEDORES!$A$3:$G$42,4,0),"") -> chef@gourmetselect.cl,contabilidad@gourmetselect.cl,pedidos@gourmetselect.cl,info@gourmetselect.cl | M258: =IFERROR(VLOOKUP(J258,PROVEEDORES!$A$3:$G$42,5,0),"") -> 56944921093 | N258: 871 | O258: CASERITA EN CASA SPA | P258: =IFERROR(VLOOKUP(O258,PROVEEDORES!$A$3:$G$42,2,0),"") -> FRUTAS Y VERDURAS | Q258: =IFERROR(VLOOKUP(O258,PROVEEDORES!$A$3:$G$42,4,0),"") -> caseritaencasa@gmail.com | R258: =IFERROR(VLOOKUP(O258,PROVEEDORES!$A$3:$G$42,5,0),"") -> 56952069703 | S258: 339 | T258: =AVERAGE(I258,N258,S258) -> 603.66667 | U258: =T258*(1+$B$2) -> 664.03333
A259: ARTICULO COCINA | B259: BROCHETAS DE COCKTAIL 50 UN | C259: UN | D259: 0.1 | E259: Bidfood Chile SA | F259: =IFERROR(VLOOKUP(E259,PROVEEDORES!$A$3:$G$42,2,0),"") -> ABARROTES | G259: =IFERROR(VLOOKUP(E259,PROVEEDORES!$A$3:$G$42,4,0),"") -> pagos@bidfood.cl,pmolina@bidfood.cl | H259: =IFERROR(VLOOKUP(E259,PROVEEDORES!$A$3:$G$42,5,0),"") -> 56225994444 - 56998038459 | I259: 2513 | J259: GOURMET SELECT LTDA | K259: =IFERROR(VLOOKUP(J259,PROVEEDORES!$A$3:$G$42,2,0),"") -> ESPECIES | L259: =IFERROR(VLOOKUP(J259,PROVEEDORES!$A$3:$G$42,4,0),"") -> chef@gourmetselect.cl,contabilidad@gourmetselect.cl,pedidos@gourmetselect.cl,info@gourmetselect.cl | M259: =IFERROR(VLOOKUP(J259,PROVEEDORES!$A$3:$G$42,5,0),"") -> 56944921093 | N259: 873 | O259: CASERITA EN CASA SPA | P259: =IFERROR(VLOOKUP(O259,PROVEEDORES!$A$3:$G$42,2,0),"") -> FRUTAS Y VERDURAS | Q259: =IFERROR(VLOOKUP(O259,PROVEEDORES!$A$3:$G$42,4,0),"") -> caseritaencasa@gmail.com | R259: =IFERROR(VLOOKUP(O259,PROVEEDORES!$A$3:$G$42,5,0),"") -> 56952069703 | S259: 3469 | T259: =AVERAGE(I259,N259,S259) -> 2285 | U259: =T259*(1+$B$2) -> 2513.5
A260: ARTICULO COCINA | B260: CAJA PLUMAVIT DE 3L PARA HELADOS | C260: UN | D260: 0.5 | E260: Bidfood Chile SA | F260: =IFERROR(VLOOKUP(E260,PROVEEDORES!$A$3:$G$42,2,0),"") -> ABARROTES | G260: =IFERROR(VLOOKUP(E260,PROVEEDORES!$A$3:$G$42,4,0),"") -> pagos@bidfood.cl,pmolina@bidfood.cl | H260: =IFERROR(VLOOKUP(E260,PROVEEDORES!$A$3:$G$42,5,0),"") -> 56225994444 - 56998038459 | I260: 2390 | J260: GOURMET SELECT LTDA | K260: =IFERROR(VLOOKUP(J260,PROVEEDORES!$A$3:$G$42,2,0),"") -> ESPECIES | L260: =IFERROR(VLOOKUP(J260,PROVEEDORES!$A$3:$G$42,4,0),"") -> chef@gourmetselect.cl,contabilidad@gourmetselect.cl,pedidos@gourmetselect.cl,info@gourmetselect.cl | M260: =IFERROR(VLOOKUP(J260,PROVEEDORES!$A$3:$G$42,5,0),"") -> 56944921093 | N260: 2261 | O260: CASERITA EN CASA SPA | P260: =IFERROR(VLOOKUP(O260,PROVEEDORES!$A$3:$G$42,2,0),"") -> FRUTAS Y VERDURAS | Q260: =IFERROR(VLOOKUP(O260,PROVEEDORES!$A$3:$G$42,4,0),"") -> caseritaencasa@gmail.com | R260: =IFERROR(VLOOKUP(O260,PROVEEDORES!$A$3:$G$42,5,0),"") -> 56952069703 | S260: 1801 | T260: =AVERAGE(I260,N260,S260) -> 2150.6667 | U260: =T260*(1+$B$2) -> 2365.7333
A261: ARTICULO COCINA | B261: CAPSULAS CERECINADAS N°8 | C261: UN | D261: 2.5 | E261: Bidfood Chile SA | F261: =IFERROR(VLOOKUP(E261,PROVEEDORES!$A$3:$G$42,2,0),"") -> ABARROTES | G261: =IFERROR(VLOOKUP(E261,PROVEEDORES!$A$3:$G$42,4,0),"") -> pagos@bidfood.cl,pmolina@bidfood.cl | H261: =IFERROR(VLOOKUP(E261,PROVEEDORES!$A$3:$G$42,5,0),"") -> 56225994444 - 56998038459 | I261: 95 | J261: GOURMET SELECT LTDA | K261: =IFERROR(VLOOKUP(J261,PROVEEDORES!$A$3:$G$42,2,0),"") -> ESPECIES | L261: =IFERROR(VLOOKUP(J261,PROVEEDORES!$A$3:$G$42,4,0),"") -> chef@gourmetselect.cl,contabilidad@gourmetselect.cl,pedidos@gourmetselect.cl,info@gourmetselect.cl | M261: =IFERROR(VLOOKUP(J261,PROVEEDORES!$A$3:$G$42,5,0),"") -> 56944921093 | N261: 28 | O261: CASERITA EN CASA SPA | P261: =IFERROR(VLOOKUP(O261,PROVEEDORES!$A$3:$G$42,2,0),"") -> FRUTAS Y VERDURAS | Q261: =IFERROR(VLOOKUP(O261,PROVEEDORES!$A$3:$G$42,4,0),"") -> caseritaencasa@gmail.com | R261: =IFERROR(VLOOKUP(O261,PROVEEDORES!$A$3:$G$42,5,0),"") -> 56952069703 | S261: 128 | T261: =AVERAGE(I261,N261,S261) -> 83.666667 | U261: =T261*(1+$B$2) -> 92.033333
A262: ARTICULO COCINA | B262: CARGA DE SIFON | C262: UN | D262: 2 | E262: Bidfood Chile SA | F262: =IFERROR(VLOOKUP(E262,PROVEEDORES!$A$3:$G$42,2,0),"") -> ABARROTES | G262: =IFERROR(VLOOKUP(E262,PROVEEDORES!$A$3:$G$42,4,0),"") -> pagos@bidfood.cl,pmolina@bidfood.cl | H262: =IFERROR(VLOOKUP(E262,PROVEEDORES!$A$3:$G$42,5,0),"") -> 56225994444 - 56998038459 | I262: 1980 | J262: GOURMET SELECT LTDA | K262: =IFERROR(VLOOKUP(J262,PROVEEDORES!$A$3:$G$42,2,0),"") -> ESPECIES | L262: =IFERROR(VLOOKUP(J262,PROVEEDORES!$A$3:$G$42,4,0),"") -> chef@gourmetselect.cl,contabilidad@gourmetselect.cl,pedidos@gourmetselect.cl,info@gourmetselect.cl | M262: =IFERROR(VLOOKUP(J262,PROVEEDORES!$A$3:$G$42,5,0),"") -> 56944921093 | N262: 2482 | O262: CASERITA EN CASA SPA | P262: =IFERROR(VLOOKUP(O262,PROVEEDORES!$A$3:$G$42,2,0),"") -> FRUTAS Y VERDURAS | Q262: =IFERROR(VLOOKUP(O262,PROVEEDORES!$A$3:$G$42,4,0),"") -> caseritaencasa@gmail.com | R262: =IFERROR(VLOOKUP(O262,PROVEEDORES!$A$3:$G$42,5,0),"") -> 56952069703 | S262: 664 | T262: =AVERAGE(I262,N262,S262) -> 1708.6667 | U262: =T262*(1+$B$2) -> 1879.5333
... A284: ARTICULO COCINA | B284: VASOS TERMICOS | C284: UN | D284: 1.75 | E284: Bidfood Chile SA | F284: =IFERROR(VLOOKUP(E284,PROVEEDORES!$A$3:$G$42,2,0),"") -> ABARROTES | G284: =IFERROR(VLOOKUP(E284,PROVEEDORES!$A$3:$G$42,4,0),"") -> pagos@bidfood.cl,pmolina@bidfood.cl | H284: =IFERROR(VLOOKUP(E284,PROVEEDORES!$A$3:$G$42,5,0),"") -> 56225994444 - 56998038459 | I284: 25 | J284: GOURMET SELECT LTDA | K284: =IFERROR(VLOOKUP(J284,PROVEEDORES!$A$3:$G$42,2,0),"") -> ESPECIES | L284: =IFERROR(VLOOKUP(J284,PROVEEDORES!$A$3:$G$42,4,0),"") -> chef@gourmetselect.cl,contabilidad@gourmetselect.cl,pedidos@gourmetselect.cl,info@gourmetselect.cl | M284: =IFERROR(VLOOKUP(J284,PROVEEDORES!$A$3:$G$42,5,0),"") -> 56944921093 | N284: 27 | O284: CASERITA EN CASA SPA | P284: =IFERROR(VLOOKUP(O284,PROVEEDORES!$A$3:$G$42,2,0),"") -> FRUTAS Y VERDURAS | Q284: =IFERROR(VLOOKUP(O284,PROVEEDORES!$A$3:$G$42,4,0),"") -> caseritaencasa@gmail.com | R284: =IFERROR(VLOOKUP(O284,PROVEEDORES!$A$3:$G$42,5,0),"") -> 56952069703 | S284: 2 | T284: =AVERAGE(I284,N284,S284) -> 18 | U284: =T284*(1+$B$2) -> 19.8
A285: BROTES
A286: BROTES | B286: MIX MICROGREENS | C286: UN | D286: 0.1 | E286: Bidfood Chile SA | F286: =IFERROR(VLOOKUP(E286,PROVEEDORES!$A$3:$G$42,2,0),"") -> ABARROTES | G286: =IFERROR(VLOOKUP(E286,PROVEEDORES!$A$3:$G$42,4,0),"") -> pagos@bidfood.cl,pmolina@bidfood.cl | H286: =IFERROR(VLOOKUP(E286,PROVEEDORES!$A$3:$G$42,5,0),"") -> 56225994444 - 56998038459 | I286: 4100 | J286: GOURMET SELECT LTDA | K286: =IFERROR(VLOOKUP(J286,PROVEEDORES!$A$3:$G$42,2,0),"") -> ESPECIES | L286: =IFERROR(VLOOKUP(J286,PROVEEDORES!$A$3:$G$42,4,0),"") -> chef@gourmetselect.cl,contabilidad@gourmetselect.cl,pedidos@gourmetselect.cl,info@gourmetselect.cl | M286: =IFERROR(VLOOKUP(J286,PROVEEDORES!$A$3:$G$42,5,0),"") -> 56944921093 | N286: 3048 | O286: CASERITA EN CASA SPA | P286: =IFERROR(VLOOKUP(O286,PROVEEDORES!$A$3:$G$42,2,0),"") -> FRUTAS Y VERDURAS | Q286: =IFERROR(VLOOKUP(O286,PROVEEDORES!$A$3:$G$42,4,0),"") -> caseritaencasa@gmail.com | R286: =IFERROR(VLOOKUP(O286,PROVEEDORES!$A$3:$G$42,5,0),"") -> 56952069703 | S286: 2603 | T286: =AVERAGE(I286,N286,S286) -> 3250.3333 | U286: =T286*(1+$B$2) -> 3575.3667
A287: CABRITO
A288: CABRITO | B288: CABRITO | C288: kg | D288: 0.1 | E288: Bidfood Chile SA | F288: =IFERROR(VLOOKUP(E288,PROVEEDORES!$A$3:$G$42,2,0),"") -> ABARROTES | G288: =IFERROR(VLOOKUP(E288,PROVEEDORES!$A$3:$G$42,4,0),"") -> pagos@bidfood.cl,pmolina@bidfood.cl | H288: =IFERROR(VLOOKUP(E288,PROVEEDORES!$A$3:$G$42,5,0),"") -> 56225994444 - 56998038459 | I288: 33000 | J288: GOURMET SELECT LTDA | K288: =IFERROR(VLOOKUP(J288,PROVEEDORES!$A$3:$G$42,2,0),"") -> ESPECIES | L288: =IFERROR(VLOOKUP(J288,PROVEEDORES!$A$3:$G$42,4,0),"") -> chef@gourmetselect.cl,contabilidad@gourmetselect.cl,pedidos@gourmetselect.cl,info@gourmetselect.cl | M288: =IFERROR(VLOOKUP(J288,PROVEEDORES!$A$3:$G$42,5,0),"") -> 56944921093 | N288: 10676 | O288: CASERITA EN CASA SPA | P288: =IFERROR(VLOOKUP(O288,PROVEEDORES!$A$3:$G$42,2,0),"") -> FRUTAS Y VERDURAS | Q288: =IFERROR(VLOOKUP(O288,PROVEEDORES!$A$3:$G$42,4,0),"") -> caseritaencasa@gmail.com | R288: =IFERROR(VLOOKUP(O288,PROVEEDORES!$A$3:$G$42,5,0),"") -> 56952069703 | S288: 22691 | T288: =AVERAGE(I288,N288,S288) -> 22122.333 | U288: =T288*(1+$B$2) -> 24334.567
A289: CERDO
A290: CERDO | B290: BUTIFARRA | C290: kg | D290: 0.0375 | E290: SOCIEDAD GANADERA RODRIGUEZ Y GRASSI CIA LTDA | F290: =IFERROR(VLOOKUP(E290,PROVEEDORES!$A$3:$G$42,2,0),"") -> CARNES | G290: =IFERROR(VLOOKUP(E290,PROVEEDORES!$A$3:$G$42,4,0),"") -> gr.ganaderareal@gmail.com | H290: =IFERROR(VLOOKUP(E290,PROVEEDORES!$A$3:$G$42,5,0),"") -> 56983670527 | I290: 11388 | J290: PALAIS GOURMET LIMITADA | K290: =IFERROR(VLOOKUP(J290,PROVEEDORES!$A$3:$G$42,2,0),"") -> CARNES Y LACTEOS | L290: =IFERROR(VLOOKUP(J290,PROVEEDORES!$A$3:$G$42,4,0),"") -> grivas@palaisgourmet.cl | M290: =IFERROR(VLOOKUP(J290,PROVEEDORES!$A$3:$G$42,5,0),"") -> 56942132129 | N290: 15590 | T290: =AVERAGE(I290,N290) -> 13489 | U290: =T290*(1+$B$2) -> 14837.9
A291: CERDO | B291: CERDO CARNE MOLIDA | C291: kg | D291: 0.03 | E291: SOCIEDAD GANADERA RODRIGUEZ Y GRASSI CIA LTDA | F291: =IFERROR(VLOOKUP(E291,PROVEEDORES!$A$3:$G$42,2,0),"") -> CARNES | G291: =IFERROR(VLOOKUP(E291,PROVEEDORES!$A$3:$G$42,4,0),"") -> gr.ganaderareal@gmail.com | H291: =IFERROR(VLOOKUP(E291,PROVEEDORES!$A$3:$G$42,5,0),"") -> 56983670527 | I291: 19485 | J291: PALAIS GOURMET LIMITADA | K291: =IFERROR(VLOOKUP(J291,PROVEEDORES!$A$3:$G$42,2,0),"") -> CARNES Y LACTEOS | L291: =IFERROR(VLOOKUP(J291,PROVEEDORES!$A$3:$G$42,4,0),"") -> grivas@palaisgourmet.cl | M291: =IFERROR(VLOOKUP(J291,PROVEEDORES!$A$3:$G$42,5,0),"") -> 56942132129 | N291: 32930 | T291: =AVERAGE(I291,N291) -> 26207.5 | U291: =T291*(1+$B$2) -> 28828.25
A292: CERDO | B292: CERDO CHULETA CENTRO TRES CM | C292: UN | D292: 0.5 | E292: SOCIEDAD GANADERA RODRIGUEZ Y GRASSI CIA LTDA | F292: =IFERROR(VLOOKUP(E292,PROVEEDORES!$A$3:$G$42,2,0),"") -> CARNES | G292: =IFERROR(VLOOKUP(E292,PROVEEDORES!$A$3:$G$42,4,0),"") -> gr.ganaderareal@gmail.com | H292: =IFERROR(VLOOKUP(E292,PROVEEDORES!$A$3:$G$42,5,0),"") -> 56983670527 | I292: 3300 | J292: PALAIS GOURMET LIMITADA | K292: =IFERROR(VLOOKUP(J292,PROVEEDORES!$A$3:$G$42,2,0),"") -> CARNES Y LACTEOS | L292: =IFERROR(VLOOKUP(J292,PROVEEDORES!$A$3:$G$42,4,0),"") -> grivas@palaisgourmet.cl | M292: =IFERROR(VLOOKUP(J292,PROVEEDORES!$A$3:$G$42,5,0),"") -> 56942132129 | N292: 3112 | T292: =AVERAGE(I292,N292) -> 3206 | U292: =T292*(1+$B$2) -> 3526.6
A293: CERDO | B293: CERDO COSTILLAR | C293: kg | D293: 0.225 | E293: SOCIEDAD GANADERA RODRIGUEZ Y GRASSI CIA LTDA | F293: =IFERROR(VLOOKUP(E293,PROVEEDORES!$A$3:$G$42,2,0),"") -> CARNES | G293: =IFERROR(VLOOKUP(E293,PROVEEDORES!$A$3:$G$42,4,0),"") -> gr.ganaderareal@gmail.com | H293: =IFERROR(VLOOKUP(E293,PROVEEDORES!$A$3:$G$42,5,0),"") -> 56983670527 | I293: 11388 | J293: PALAIS GOURMET LIMITADA | K293: =IFERROR(VLOOKUP(J293,PROVEEDORES!$A$3:$G$42,2,0),"") -> CARNES Y LACTEOS | L293: =IFERROR(VLOOKUP(J293,PROVEEDORES!$A$3:$G$42,4,0),"") -> grivas@palaisgourmet.cl | M293: =IFERROR(VLOOKUP(J293,PROVEEDORES!$A$3:$G$42,5,0),"") -> 56942132129 | N293: 15231 | T293: =AVERAGE(I293,N293) -> 13309.5 | U293: =T293*(1+$B$2) -> 14640.45
A294: CERDO | B294: CERDO CUERO | C294: kg | D294: 0.03 | E294: SOCIEDAD GANADERA RODRIGUEZ Y GRASSI CIA LTDA | F294: =IFERROR(VLOOKUP(E294,PROVEEDORES!$A$3:$G$42,2,0),"") -> CARNES | G294: =IFERROR(VLOOKUP(E294,PROVEEDORES!$A$3:$G$42,4,0),"") -> gr.ganaderareal@gmail.com | H294: =IFERROR(VLOOKUP(E294,PROVEEDORES!$A$3:$G$42,5,0),"") -> 56983670527 | I294: 4605 | J294: PALAIS GOURMET LIMITADA | K294: =IFERROR(VLOOKUP(J294,PROVEEDORES!$A$3:$G$42,2,0),"") -> CARNES Y LACTEOS | L294: =IFERROR(VLOOKUP(J294,PROVEEDORES!$A$3:$G$42,4,0),"") -> grivas@palaisgourmet.cl | M294: =IFERROR(VLOOKUP(J294,PROVEEDORES!$A$3:$G$42,5,0),"") -> 56942132129 | N294: 6705 | T294: =AVERAGE(I294,N294) -> 5655 | U294: =T294*(1+$B$2) -> 6220.5
A295: CERDO | B295: CERDO GRASA/TOCINO BLANCO | C295: kg | D295: 0.318125 | E295: SOCIEDAD GANADERA RODRIGUEZ Y GRASSI CIA LTDA | F295: =IFERROR(VLOOKUP(E295,PROVEEDORES!$A$3:$G$42,2,0),"") -> CARNES | G295: =IFERROR(VLOOKUP(E295,PROVEEDORES!$A$3:$G$42,4,0),"") -> gr.ganaderareal@gmail.com | H295: =IFERROR(VLOOKUP(E295,PROVEEDORES!$A$3:$G$42,5,0),"") -> 56983670527 | I295: 3534 | J295: PALAIS GOURMET LIMITADA | K295: =IFERROR(VLOOKUP(J295,PROVEEDORES!$A$3:$G$42,2,0),"") -> CARNES Y LACTEOS | L295: =IFERROR(VLOOKUP(J295,PROVEEDORES!$A$3:$G$42,4,0),"") -> grivas@palaisgourmet.cl | M295: =IFERROR(VLOOKUP(J295,PROVEEDORES!$A$3:$G$42,5,0),"") -> 56942132129 | N295: 4605 | T295: =AVERAGE(I295,N295) -> 4069.5 | U295: =T295*(1+$B$2) -> 4476.45
A296: CERDO | B296: CERDO LOMO CENTRO | C296: kg | D296: 0.46625 | E296: SOCIEDAD GANADERA RODRIGUEZ Y GRASSI CIA LTDA | F296: =IFERROR(VLOOKUP(E296,PROVEEDORES!$A$3:$G$42,2,0),"") -> CARNES | G296: =IFERROR(VLOOKUP(E296,PROVEEDORES!$A$3:$G$42,4,0),"") -> gr.ganaderareal@gmail.com | H296: =IFERROR(VLOOKUP(E296,PROVEEDORES!$A$3:$G$42,5,0),"") -> 56983670527 | I296: 9420 | J296: PALAIS GOURMET LIMITADA | K296: =IFERROR(VLOOKUP(J296,PROVEEDORES!$A$3:$G$42,2,0),"") -> CARNES Y LACTEOS | L296: =IFERROR(VLOOKUP(J296,PROVEEDORES!$A$3:$G$42,4,0),"") -> grivas@palaisgourmet.cl | M296: =IFERROR(VLOOKUP(J296,PROVEEDORES!$A$3:$G$42,5,0),"") -> 56942132129 | N296: 14238 | T296: =AVERAGE(I296,N296) -> 11829 | U296: =T296*(1+$B$2) -> 13011.9
A297: CERDO | B297: CERDO LOMO TUNGO | C297: kg | D297: 0.06 | E297: SOCIEDAD GANADERA RODRIGUEZ Y GRASSI CIA LTDA | F297: =IFERROR(VLOOKUP(E297,PROVEEDORES!$A$3:$G$42,2,0),"") -> CARNES | G297: =IFERROR(VLOOKUP(E297,PROVEEDORES!$A$3:$G$42,4,0),"") -> gr.ganaderareal@gmail.com | H297: =IFERROR(VLOOKUP(E297,PROVEEDORES!$A$3:$G$42,5,0),"") -> 56983670527 | I297: 12102 | J297: PALAIS GOURMET LIMITADA | K297: =IFERROR(VLOOKUP(J297,PROVEEDORES!$A$3:$G$42,2,0),"") -> CARNES Y LACTEOS | L297: =IFERROR(VLOOKUP(J297,PROVEEDORES!$A$3:$G$42,4,0),"") -> grivas@palaisgourmet.cl | M297: =IFERROR(VLOOKUP(J297,PROVEEDORES!$A$3:$G$42,5,0),"") -> 56942132129 | N297: 11957 | T297: =AVERAGE(I297,N297) -> 12029.5 | U297: =T297*(1+$B$2) -> 13232.45
A298: CERDO | B298: CERDO MALAYA | C298: kg | D298: 0.125 | E298: SOCIEDAD GANADERA RODRIGUEZ Y GRASSI CIA LTDA | F298: =IFERROR(VLOOKUP(E298,PROVEEDORES!$A$3:$G$42,2,0),"") -> CARNES | G298: =IFERROR(VLOOKUP(E298,PROVEEDORES!$A$3:$G$42,4,0),"") -> gr.ganaderareal@gmail.com | H298: =IFERROR(VLOOKUP(E298,PROVEEDORES!$A$3:$G$42,5,0),"") -> 56983670527 | I298: 17993 | J298: PALAIS GOURMET LIMITADA | K298: =IFERROR(VLOOKUP(J298,PROVEEDORES!$A$3:$G$42,2,0),"") -> CARNES Y LACTEOS | L298: =IFERROR(VLOOKUP(J298,PROVEEDORES!$A$3:$G$42,4,0),"") -> grivas@palaisgourmet.cl | M298: =IFERROR(VLOOKUP(J298,PROVEEDORES!$A$3:$G$42,5,0),"") -> 56942132129 | N298: 21826 | T298: =AVERAGE(I298,N298) -> 19909.5 | U298: =T298*(1+$B$2) -> 21900.45
A299: CERDO | B299: CERDO PALETA DESHUESADA | C299: kg | D299: 0.084375 | E299: SOCIEDAD GANADERA RODRIGUEZ Y GRASSI CIA LTDA | F299: =IFERROR(VLOOKUP(E299,PROVEEDORES!$A$3:$G$42,2,0),"") -> CARNES | G299: =IFERROR(VLOOKUP(E299,PROVEEDORES!$A$3:$G$42,4,0),"") -> gr.ganaderareal@gmail.com | H299: =IFERROR(VLOOKUP(E299,PROVEEDORES!$A$3:$G$42,5,0),"") -> 56983670527 | I299: 8970 | J299: PALAIS GOURMET LIMITADA | K299: =IFERROR(VLOOKUP(J299,PROVEEDORES!$A$3:$G$42,2,0),"") -> CARNES Y LACTEOS | L299: =IFERROR(VLOOKUP(J299,PROVEEDORES!$A$3:$G$42,4,0),"") -> grivas@palaisgourmet.cl | M299: =IFERROR(VLOOKUP(J299,PROVEEDORES!$A$3:$G$42,5,0),"") -> 56942132129 | N299: 15025 | T299: =AVERAGE(I299,N299) -> 11997.5 | U299: =T299*(1+$B$2) -> 13197.25
A300: CERDO | B300: CERDO PATAS | C300: UN | D300: 0.5 | E300: SOCIEDAD GANADERA RODRIGUEZ Y GRASSI CIA LTDA | F300: =IFERROR(VLOOKUP(E300,PROVEEDORES!$A$3:$G$42,2,0),"") -> CARNES | G300: =IFERROR(VLOOKUP(E300,PROVEEDORES!$A$3:$G$42,4,0),"") -> gr.ganaderareal@gmail.com | H300: =IFERROR(VLOOKUP(E300,PROVEEDORES!$A$3:$G$42,5,0),"") -> 56983670527 | I300: 4320 | J300: PALAIS GOURMET LIMITADA | K300: =IFERROR(VLOOKUP(J300,PROVEEDORES!$A$3:$G$42,2,0),"") -> CARNES Y LACTEOS | L300: =IFERROR(VLOOKUP(J300,PROVEEDORES!$A$3:$G$42,4,0),"") -> grivas@palaisgourmet.cl | M300: =IFERROR(VLOOKUP(J300,PROVEEDORES!$A$3:$G$42,5,0),"") -> 56942132129 | N300: 1981 | T300: =AVERAGE(I300,N300) -> 3150.5 | U300: =T300*(1+$B$2) -> 3465.55
A301: CERDO | B301: CERDO PERNIL DE MANO | C301: kg | D301: 0.2 | E301: SOCIEDAD GANADERA RODRIGUEZ Y GRASSI CIA LTDA | F301: =IFERROR(VLOOKUP(E301,PROVEEDORES!$A$3:$G$42,2,0),"") -> CARNES | G301: =IFERROR(VLOOKUP(E301,PROVEEDORES!$A$3:$G$42,4,0),"") -> gr.ganaderareal@gmail.com | H301: =IFERROR(VLOOKUP(E301,PROVEEDORES!$A$3:$G$42,5,0),"") -> 56983670527 | I301: 5370 | J301: PALAIS GOURMET LIMITADA | K301: =IFERROR(VLOOKUP(J301,PROVEEDORES!$A$3:$G$42,2,0),"") -> CARNES Y LACTEOS | L301: =IFERROR(VLOOKUP(J301,PROVEEDORES!$A$3:$G$42,4,0),"") -> grivas@palaisgourmet.cl | M301: =IFERROR(VLOOKUP(J301,PROVEEDORES!$A$3:$G$42,5,0),"") -> 56942132129 | N301: 8455 | T301: =AVERAGE(I301,N301) -> 6912.5 | U301: =T301*(1+$B$2) -> 7603.75
... A310: CERDO | B310: TRIPAS DE CERDO FRESCA | C310: kg | D310: 0.03375 | E310: SOCIEDAD GANADERA RODRIGUEZ Y GRASSI CIA LTDA | F310: =IFERROR(VLOOKUP(E310,PROVEEDORES!$A$3:$G$42,2,0),"") -> CARNES | G310: =IFERROR(VLOOKUP(E310,PROVEEDORES!$A$3:$G$42,4,0),"") -> gr.ganaderareal@gmail.com | H310: =IFERROR(VLOOKUP(E310,PROVEEDORES!$A$3:$G$42,5,0),"") -> 56983670527 | I310: 25470 | J310: PALAIS GOURMET LIMITADA | K310: =IFERROR(VLOOKUP(J310,PROVEEDORES!$A$3:$G$42,2,0),"") -> CARNES Y LACTEOS | L310: =IFERROR(VLOOKUP(J310,PROVEEDORES!$A$3:$G$42,4,0),"") -> grivas@palaisgourmet.cl | M310: =IFERROR(VLOOKUP(J310,PROVEEDORES!$A$3:$G$42,5,0),"") -> 56942132129 | N310: 11258 | T310: =AVERAGE(I310,N310) -> 18364 | U310: =T310*(1+$B$2) -> 20200.4
A311: CERVEZA
A312: CERVEZA | B312: CERVEZA CRISTAL | C312: L | D312: 0.085 | E312: La Vinoteca | F312: =IFERROR(VLOOKUP(E312,PROVEEDORES!$A$3:$G$42,2,0),"") -> VINOS Y LICORES | G312: =IFERROR(VLOOKUP(E312,PROVEEDORES!$A$3:$G$42,4,0),"") -> andrea.aristizabal@lavinoteca.cl, johanna.quiroga@lavinoteca.cl, margarita.arias@lavinoteca.cl | H312: =IFERROR(VLOOKUP(E312,PROVEEDORES!$A$3:$G$42,5,0),"") -> 56228292221 - 56992197824 | I312: 3909 | J312: Bidfood Chile SA | K312: =IFERROR(VLOOKUP(J312,PROVEEDORES!$A$3:$G$42,2,0),"") -> ABARROTES | L312: =IFERROR(VLOOKUP(J312,PROVEEDORES!$A$3:$G$42,4,0),"") -> pagos@bidfood.cl,pmolina@bidfood.cl | M312: =IFERROR(VLOOKUP(J312,PROVEEDORES!$A$3:$G$42,5,0),"") -> 56225994444 - 56998038459 | N312: 6501 | T312: =AVERAGE(I312,N312) -> 5205 | U312: =T312*(1+$B$2) -> 5725.5
A313: CHOCOLATE
A314: CHOCOLATE | B314: BATON 500 PETIT PAIN 3,2GR | C314: UN | D314: 12 | E314: NEUCOBER S.A | F314: =IFERROR(VLOOKUP(E314,PROVEEDORES!$A$3:$G$42,2,0),"") -> CHOCOLATE | G314: =IFERROR(VLOOKUP(E314,PROVEEDORES!$A$3:$G$42,4,0),"") -> danielgonzalez@neucober.cl | H314: =IFERROR(VLOOKUP(E314,PROVEEDORES!$A$3:$G$42,5,0),"") -> 56978895811 | I314: 63 | J314: Agrogourmet | K314: =IFERROR(VLOOKUP(J314,PROVEEDORES!$A$3:$G$42,2,0),"") -> Chocolateria | L314: =IFERROR(VLOOKUP(J314,PROVEEDORES!$A$3:$G$42,4,0),"") -> carolina@agourmet.cl | M314: =IFERROR(VLOOKUP(J314,PROVEEDORES!$A$3:$G$42,5,0),"") -> 56990220710 | N314: 66 | O314: GOURMET SELECT LTDA | P314: =IFERROR(VLOOKUP(O314,PROVEEDORES!$A$3:$G$42,2,0),"") -> ESPECIES | Q314: =IFERROR(VLOOKUP(O314,PROVEEDORES!$A$3:$G$42,4,0),"") -> chef@gourmetselect.cl,contabilidad@gourmetselect.cl,pedidos@gourmetselect.cl,info@gourmetselect.cl | R314: =IFERROR(VLOOKUP(O314,PROVEEDORES!$A$3:$G$42,5,0),"") -> 56944921093 | S314: 126 | T314: =AVERAGE(I314,N314,S314) -> 85 | U314: =T314*(1+$B$2) -> 93.5
A315: CHOCOLATE | B315: CACAO EN POLVO ALCALINO | C315: kg | D315: 0.357 | E315: NEUCOBER S.A | F315: =IFERROR(VLOOKUP(E315,PROVEEDORES!$A$3:$G$42,2,0),"") -> CHOCOLATE | G315: =IFERROR(VLOOKUP(E315,PROVEEDORES!$A$3:$G$42,4,0),"") -> danielgonzalez@neucober.cl | H315: =IFERROR(VLOOKUP(E315,PROVEEDORES!$A$3:$G$42,5,0),"") -> 56978895811 | I315: 11662 | J315: Agrogourmet | K315: =IFERROR(VLOOKUP(J315,PROVEEDORES!$A$3:$G$42,2,0),"") -> Chocolateria | L315: =IFERROR(VLOOKUP(J315,PROVEEDORES!$A$3:$G$42,4,0),"") -> carolina@agourmet.cl | M315: =IFERROR(VLOOKUP(J315,PROVEEDORES!$A$3:$G$42,5,0),"") -> 56990220710 | N315: 16508 | O315: GOURMET SELECT LTDA | P315: =IFERROR(VLOOKUP(O315,PROVEEDORES!$A$3:$G$42,2,0),"") -> ESPECIES | Q315: =IFERROR(VLOOKUP(O315,PROVEEDORES!$A$3:$G$42,4,0),"") -> chef@gourmetselect.cl,contabilidad@gourmetselect.cl,pedidos@gourmetselect.cl,info@gourmetselect.cl | R315: =IFERROR(VLOOKUP(O315,PROVEEDORES!$A$3:$G$42,5,0),"") -> 56944921093 | S315: 18025 | T315: =AVERAGE(I315,N315,S315) -> 15398.333 | U315: =T315*(1+$B$2) -> 16938.167
A316: CHOCOLATE | B316: CACAO EN POLVO AMARGO | C316: kg | D316: 0.217625 | E316: NEUCOBER S.A | F316: =IFERROR(VLOOKUP(E316,PROVEEDORES!$A$3:$G$42,2,0),"") -> CHOCOLATE | G316: =IFERROR(VLOOKUP(E316,PROVEEDORES!$A$3:$G$42,4,0),"") -> danielgonzalez@neucober.cl | H316: =IFERROR(VLOOKUP(E316,PROVEEDORES!$A$3:$G$42,5,0),"") -> 56978895811 | I316: 9786 | J316: Agrogourmet | K316: =IFERROR(VLOOKUP(J316,PROVEEDORES!$A$3:$G$42,2,0),"") -> Chocolateria | L316: =IFERROR(VLOOKUP(J316,PROVEEDORES!$A$3:$G$42,4,0),"") -> carolina@agourmet.cl | M316: =IFERROR(VLOOKUP(J316,PROVEEDORES!$A$3:$G$42,5,0),"") -> 56990220710 | N316: 8553 | O316: GOURMET SELECT LTDA | P316: =IFERROR(VLOOKUP(O316,PROVEEDORES!$A$3:$G$42,2,0),"") -> ESPECIES | Q316: =IFERROR(VLOOKUP(O316,PROVEEDORES!$A$3:$G$42,4,0),"") -> chef@gourmetselect.cl,contabilidad@gourmetselect.cl,pedidos@gourmetselect.cl,info@gourmetselect.cl | R316: =IFERROR(VLOOKUP(O316,PROVEEDORES!$A$3:$G$42,5,0),"") -> 56944921093 | S316: 141 | T316: =AVERAGE(I316,N316,S316) -> 6160 | U316: =T316*(1+$B$2) -> 6776
A317: CHOCOLATE | B317: CHIPS DE CHOCOLATE | C317: kg | D317: 0.055 | E317: NEUCOBER S.A | F317: =IFERROR(VLOOKUP(E317,PROVEEDORES!$A$3:$G$42,2,0),"") -> CHOCOLATE | G317: =IFERROR(VLOOKUP(E317,PROVEEDORES!$A$3:$G$42,4,0),"") -> danielgonzalez@neucober.cl | H317: =IFERROR(VLOOKUP(E317,PROVEEDORES!$A$3:$G$42,5,0),"") -> 56978895811 | I317: 16169 | J317: Agrogourmet | K317: =IFERROR(VLOOKUP(J317,PROVEEDORES!$A$3:$G$42,2,0),"") -> Chocolateria | L317: =IFERROR(VLOOKUP(J317,PROVEEDORES!$A$3:$G$42,4,0),"") -> carolina@agourmet.cl | M317: =IFERROR(VLOOKUP(J317,PROVEEDORES!$A$3:$G$42,5,0),"") -> 56990220710 | N317: 20389 | O317: GOURMET SELECT LTDA | P317: =IFERROR(VLOOKUP(O317,PROVEEDORES!$A$3:$G$42,2,0),"") -> ESPECIES | Q317: =IFERROR(VLOOKUP(O317,PROVEEDORES!$A$3:$G$42,4,0),"") -> chef@gourmetselect.cl,contabilidad@gourmetselect.cl,pedidos@gourmetselect.cl,info@gourmetselect.cl | R317: =IFERROR(VLOOKUP(O317,PROVEEDORES!$A$3:$G$42,5,0),"") -> 56944921093 | S317: 25418 | T317: =AVERAGE(I317,N317,S317) -> 20658.667 | U317: =T317*(1+$B$2) -> 22724.533
A318: CHOCOLATE | B318: CHOCOLATE AMARGO 56% | C318: kg | D318: 0.520625 | E318: NEUCOBER S.A | F318: =IFERROR(VLOOKUP(E318,PROVEEDORES!$A$3:$G$42,2,0),"") -> CHOCOLATE | G318: =IFERROR(VLOOKUP(E318,PROVEEDORES!$A$3:$G$42,4,0),"") -> danielgonzalez@neucober.cl | H318: =IFERROR(VLOOKUP(E318,PROVEEDORES!$A$3:$G$42,5,0),"") -> 56978895811 | I318: 18894 | J318: Agrogourmet | K318: =IFERROR(VLOOKUP(J318,PROVEEDORES!$A$3:$G$42,2,0),"") -> Chocolateria | L318: =IFERROR(VLOOKUP(J318,PROVEEDORES!$A$3:$G$42,4,0),"") -> carolina@agourmet.cl | M318: =IFERROR(VLOOKUP(J318,PROVEEDORES!$A$3:$G$42,5,0),"") -> 56990220710 | N318: 13991 | O318: GOURMET SELECT LTDA | P318: =IFERROR(VLOOKUP(O318,PROVEEDORES!$A$3:$G$42,2,0),"") -> ESPECIES | Q318: =IFERROR(VLOOKUP(O318,PROVEEDORES!$A$3:$G$42,4,0),"") -> chef@gourmetselect.cl,contabilidad@gourmetselect.cl,pedidos@gourmetselect.cl,info@gourmetselect.cl | R318: =IFERROR(VLOOKUP(O318,PROVEEDORES!$A$3:$G$42,5,0),"") -> 56944921093 | S318: 36352 | T318: =AVERAGE(I318,N318,S318) -> 23079 | U318: =T318*(1+$B$2) -> 25386.9
A319: CHOCOLATE | B319: CHOCOLATE AMARGO 56% FLUIDO | C319: kg | D319: 0.47 | E319: NEUCOBER S.A | F319: =IFERROR(VLOOKUP(E319,PROVEEDORES!$A$3:$G$42,2,0),"") -> CHOCOLATE | G319: =IFERROR(VLOOKUP(E319,PROVEEDORES!$A$3:$G$42,4,0),"") -> danielgonzalez@neucober.cl | H319: =IFERROR(VLOOKUP(E319,PROVEEDORES!$A$3:$G$42,5,0),"") -> 56978895811 | I319: 18894 | J319: Agrogourmet | K319: =IFERROR(VLOOKUP(J319,PROVEEDORES!$A$3:$G$42,2,0),"") -> Chocolateria | L319: =IFERROR(VLOOKUP(J319,PROVEEDORES!$A$3:$G$42,4,0),"") -> carolina@agourmet.cl | M319: =IFERROR(VLOOKUP(J319,PROVEEDORES!$A$3:$G$42,5,0),"") -> 56990220710 | N319: 14048 | O319: GOURMET SELECT LTDA | P319: =IFERROR(VLOOKUP(O319,PROVEEDORES!$A$3:$G$42,2,0),"") -> ESPECIES | Q319: =IFERROR(VLOOKUP(O319,PROVEEDORES!$A$3:$G$42,4,0),"") -> chef@gourmetselect.cl,contabilidad@gourmetselect.cl,pedidos@gourmetselect.cl,info@gourmetselect.cl | R319: =IFERROR(VLOOKUP(O319,PROVEEDORES!$A$3:$G$42,5,0),"") -> 56944921093 | S319: 22261 | T319: =AVERAGE(I319,N319,S319) -> 18401 | U319: =T319*(1+$B$2) -> 20241.1
A320: CHOCOLATE | B320: CHOCOLATE AMARGO 65% | C320: kg | D320: 0.105 | E320: NEUCOBER S.A | F320: =IFERROR(VLOOKUP(E320,PROVEEDORES!$A$3:$G$42,2,0),"") -> CHOCOLATE | G320: =IFERROR(VLOOKUP(E320,PROVEEDORES!$A$3:$G$42,4,0),"") -> danielgonzalez@neucober.cl | H320: =IFERROR(VLOOKUP(E320,PROVEEDORES!$A$3:$G$42,5,0),"") -> 56978895811 | I320: 14647 | J320: Agrogourmet | K320: =IFERROR(VLOOKUP(J320,PROVEEDORES!$A$3:$G$42,2,0),"") -> Chocolateria | L320: =IFERROR(VLOOKUP(J320,PROVEEDORES!$A$3:$G$42,4,0),"") -> carolina@agourmet.cl | M320: =IFERROR(VLOOKUP(J320,PROVEEDORES!$A$3:$G$42,5,0),"") -> 56990220710 | N320: 5397 | O320: GOURMET SELECT LTDA | P320: =IFERROR(VLOOKUP(O320,PROVEEDORES!$A$3:$G$42,2,0),"") -> ESPECIES | Q320: =IFERROR(VLOOKUP(O320,PROVEEDORES!$A$3:$G$42,4,0),"") -> chef@gourmetselect.cl,contabilidad@gourmetselect.cl,pedidos@gourmetselect.cl,info@gourmetselect.cl | R320: =IFERROR(VLOOKUP(O320,PROVEEDORES!$A$3:$G$42,5,0),"") -> 56944921093 | S320: 24765 | T320: =AVERAGE(I320,N320,S320) -> 14936.333 | U320: =T320*(1+$B$2) -> 16429.967
A321: CHOCOLATE | B321: CHOCOLATE AMARGO 70% | C321: kg | D321: 0.2545 | E321: NEUCOBER S.A | F321: =IFERROR(VLOOKUP(E321,PROVEEDORES!$A$3:$G$42,2,0),"") -> CHOCOLATE | G321: =IFERROR(VLOOKUP(E321,PROVEEDORES!$A$3:$G$42,4,0),"") -> danielgonzalez@neucober.cl | H321: =IFERROR(VLOOKUP(E321,PROVEEDORES!$A$3:$G$42,5,0),"") -> 56978895811 | I321: 21736 | J321: Agrogourmet | K321: =IFERROR(VLOOKUP(J321,PROVEEDORES!$A$3:$G$42,2,0),"") -> Chocolateria | L321: =IFERROR(VLOOKUP(J321,PROVEEDORES!$A$3:$G$42,4,0),"") -> carolina@agourmet.cl | M321: =IFERROR(VLOOKUP(J321,PROVEEDORES!$A$3:$G$42,5,0),"") -> 56990220710 | N321: 7521 | O321: GOURMET SELECT LTDA | P321: =IFERROR(VLOOKUP(O321,PROVEEDORES!$A$3:$G$42,2,0),"") -> ESPECIES | Q321: =IFERROR(VLOOKUP(O321,PROVEEDORES!$A$3:$G$42,4,0),"") -> chef@gourmetselect.cl,contabilidad@gourmetselect.cl,pedidos@gourmetselect.cl,info@gourmetselect.cl | R321: =IFERROR(VLOOKUP(O321,PROVEEDORES!$A$3:$G$42,5,0),"") -> 56944921093 | S321: 19106 | T321: =AVERAGE(I321,N321,S321) -> 16121 | U321: =T321*(1+$B$2) -> 17733.1
A322: CHOCOLATE | B322: CHOCOLATE CALLEBAUT BLANCO 28% | C322: kg | D322: 0.42825 | E322: NEUCOBER S.A | F322: =IFERROR(VLOOKUP(E322,PROVEEDORES!$A$3:$G$42,2,0),"") -> CHOCOLATE | G322: =IFERROR(VLOOKUP(E322,PROVEEDORES!$A$3:$G$42,4,0),"") -> danielgonzalez@neucober.cl | H322: =IFERROR(VLOOKUP(E322,PROVEEDORES!$A$3:$G$42,5,0),"") -> 56978895811 | I322: 20197 | J322: Agrogourmet | K322: =IFERROR(VLOOKUP(J322,PROVEEDORES!$A$3:$G$42,2,0),"") -> Chocolateria | L322: =IFERROR(VLOOKUP(J322,PROVEEDORES!$A$3:$G$42,4,0),"") -> carolina@agourmet.cl | M322: =IFERROR(VLOOKUP(J322,PROVEEDORES!$A$3:$G$42,5,0),"") -> 56990220710 | N322: 18985 | O322: GOURMET SELECT LTDA | P322: =IFERROR(VLOOKUP(O322,PROVEEDORES!$A$3:$G$42,2,0),"") -> ESPECIES | Q322: =IFERROR(VLOOKUP(O322,PROVEEDORES!$A$3:$G$42,4,0),"") -> chef@gourmetselect.cl,contabilidad@gourmetselect.cl,pedidos@gourmetselect.cl,info@gourmetselect.cl | R322: =IFERROR(VLOOKUP(O322,PROVEEDORES!$A$3:$G$42,5,0),"") -> 56944921093 | S322: 16998 | T322: =AVERAGE(I322,N322,S322) -> 18726.667 | U322: =T322*(1+$B$2) -> 20599.333
A323: CHOCOLATE | B323: CHOCOLATE DE LECHE 33% | C323: kg | D323: 0.73 | E323: NEUCOBER S.A | F323: =IFERROR(VLOOKUP(E323,PROVEEDORES!$A$3:$G$42,2,0),"") -> CHOCOLATE | G323: =IFERROR(VLOOKUP(E323,PROVEEDORES!$A$3:$G$42,4,0),"") -> danielgonzalez@neucober.cl | H323: =IFERROR(VLOOKUP(E323,PROVEEDORES!$A$3:$G$42,5,0),"") -> 56978895811 | I323: 14360 | J323: Agrogourmet | K323: =IFERROR(VLOOKUP(J323,PROVEEDORES!$A$3:$G$42,2,0),"") -> Chocolateria | L323: =IFERROR(VLOOKUP(J323,PROVEEDORES!$A$3:$G$42,4,0),"") -> carolina@agourmet.cl | M323: =IFERROR(VLOOKUP(J323,PROVEEDORES!$A$3:$G$42,5,0),"") -> 56990220710 | N323: 8910 | O323: GOURMET SELECT LTDA | P323: =IFERROR(VLOOKUP(O323,PROVEEDORES!$A$3:$G$42,2,0),"") -> ESPECIES | Q323: =IFERROR(VLOOKUP(O323,PROVEEDORES!$A$3:$G$42,4,0),"") -> chef@gourmetselect.cl,contabilidad@gourmetselect.cl,pedidos@gourmetselect.cl,info@gourmetselect.cl | R323: =IFERROR(VLOOKUP(O323,PROVEEDORES!$A$3:$G$42,5,0),"") -> 56944921093 | S323: 12243 | T323: =AVERAGE(I323,N323,S323) -> 11837.667 | U323: =T323*(1+$B$2) -> 13021.433
A324: CHOCOLATE | B324: CHOCOLATE ECUADOR BLANCO 31% | C324: kg | D324: 0.7 | E324: NEUCOBER S.A | F324: =IFERROR(VLOOKUP(E324,PROVEEDORES!$A$3:$G$42,2,0),"") -> CHOCOLATE | G324: =IFERROR(VLOOKUP(E324,PROVEEDORES!$A$3:$G$42,4,0),"") -> danielgonzalez@neucober.cl | H324: =IFERROR(VLOOKUP(E324,PROVEEDORES!$A$3:$G$42,5,0),"") -> 56978895811 | I324: 17918 | J324: Agrogourmet | K324: =IFERROR(VLOOKUP(J324,PROVEEDORES!$A$3:$G$42,2,0),"") -> Chocolateria | L324: =IFERROR(VLOOKUP(J324,PROVEEDORES!$A$3:$G$42,4,0),"") -> carolina@agourmet.cl | M324: =IFERROR(VLOOKUP(J324,PROVEEDORES!$A$3:$G$42,5,0),"") -> 56990220710 | N324: 18563 | O324: GOURMET SELECT LTDA | P324: =IFERROR(VLOOKUP(O324,PROVEEDORES!$A$3:$G$42,2,0),"") -> ESPECIES | Q324: =IFERROR(VLOOKUP(O324,PROVEEDORES!$A$3:$G$42,4,0),"") -> chef@gourmetselect.cl,contabilidad@gourmetselect.cl,pedidos@gourmetselect.cl,info@gourmetselect.cl | R324: =IFERROR(VLOOKUP(O324,PROVEEDORES!$A$3:$G$42,5,0),"") -> 56944921093 | S324: 31951 | T324: =AVERAGE(I324,N324,S324) -> 22810.667 | U324: =T324*(1+$B$2) -> 25091.733
A325: CHOCOLATE | B325: CHOCOLATE LECHE 35% | C325: kg | D325: 0.1 | E325: NEUCOBER S.A | F325: =IFERROR(VLOOKUP(E325,PROVEEDORES!$A$3:$G$42,2,0),"") -> CHOCOLATE | G325: =IFERROR(VLOOKUP(E325,PROVEEDORES!$A$3:$G$42,4,0),"") -> danielgonzalez@neucober.cl | H325: =IFERROR(VLOOKUP(E325,PROVEEDORES!$A$3:$G$42,5,0),"") -> 56978895811 | I325: 20036 | J325: Agrogourmet | K325: =IFERROR(VLOOKUP(J325,PROVEEDORES!$A$3:$G$42,2,0),"") -> Chocolateria | L325: =IFERROR(VLOOKUP(J325,PROVEEDORES!$A$3:$G$42,4,0),"") -> carolina@agourmet.cl | M325: =IFERROR(VLOOKUP(J325,PROVEEDORES!$A$3:$G$42,5,0),"") -> 56990220710 | N325: 34221 | O325: GOURMET SELECT LTDA | P325: =IFERROR(VLOOKUP(O325,PROVEEDORES!$A$3:$G$42,2,0),"") -> ESPECIES | Q325: =IFERROR(VLOOKUP(O325,PROVEEDORES!$A$3:$G$42,4,0),"") -> chef@gourmetselect.cl,contabilidad@gourmetselect.cl,pedidos@gourmetselect.cl,info@gourmetselect.cl | R325: =IFERROR(VLOOKUP(O325,PROVEEDORES!$A$3:$G$42,5,0),"") -> 56944921093 | S325: 9545 | T325: =AVERAGE(I325,N325,S325) -> 21267.333 | U325: =T325*(1+$B$2) -> 23394.067
... A334: CHOCOLATE | B334: MOSTACILLAS DE CHOCOLATE | C334: kg | D334: 0.005 | E334: NEUCOBER S.A | F334: =IFERROR(VLOOKUP(E334,PROVEEDORES!$A$3:$G$42,2,0),"") -> CHOCOLATE | G334: =IFERROR(VLOOKUP(E334,PROVEEDORES!$A$3:$G$42,4,0),"") -> danielgonzalez@neucober.cl | H334: =IFERROR(VLOOKUP(E334,PROVEEDORES!$A$3:$G$42,5,0),"") -> 56978895811 | I334: 6094 | J334: Agrogourmet | K334: =IFERROR(VLOOKUP(J334,PROVEEDORES!$A$3:$G$42,2,0),"") -> Chocolateria | L334: =IFERROR(VLOOKUP(J334,PROVEEDORES!$A$3:$G$42,4,0),"") -> carolina@agourmet.cl | M334: =IFERROR(VLOOKUP(J334,PROVEEDORES!$A$3:$G$42,5,0),"") -> 56990220710 | N334: 9604 | O334: GOURMET SELECT LTDA | P334: =IFERROR(VLOOKUP(O334,PROVEEDORES!$A$3:$G$42,2,0),"") -> ESPECIES | Q334: =IFERROR(VLOOKUP(O334,PROVEEDORES!$A$3:$G$42,4,0),"") -> chef@gourmetselect.cl,contabilidad@gourmetselect.cl,pedidos@gourmetselect.cl,info@gourmetselect.cl | R334: =IFERROR(VLOOKUP(O334,PROVEEDORES!$A$3:$G$42,5,0),"") -> 56944921093 | S334: 3748 | T334: =AVERAGE(I334,N334,S334) -> 6482 | U334: =T334*(1+$B$2) -> 7130.2
A335: COLORANTES
A336: COLORANTES | B336: COLORANTE GEL AZUL | C336: UN | D336: 0.11 | E336: Bidfood Chile SA | F336: =IFERROR(VLOOKUP(E336,PROVEEDORES!$A$3:$G$42,2,0),"") -> ABARROTES | G336: =IFERROR(VLOOKUP(E336,PROVEEDORES!$A$3:$G$42,4,0),"") -> pagos@bidfood.cl,pmolina@bidfood.cl | H336: =IFERROR(VLOOKUP(E336,PROVEEDORES!$A$3:$G$42,5,0),"") -> 56225994444 - 56998038459 | I336: 3800 | J336: GOURMET SELECT LTDA | K336: =IFERROR(VLOOKUP(J336,PROVEEDORES!$A$3:$G$42,2,0),"") -> ESPECIES | L336: =IFERROR(VLOOKUP(J336,PROVEEDORES!$A$3:$G$42,4,0),"") -> chef@gourmetselect.cl,contabilidad@gourmetselect.cl,pedidos@gourmetselect.cl,info@gourmetselect.cl | M336: =IFERROR(VLOOKUP(J336,PROVEEDORES!$A$3:$G$42,5,0),"") -> 56944921093 | N336: 1771 | O336: CASERITA EN CASA SPA | P336: =IFERROR(VLOOKUP(O336,PROVEEDORES!$A$3:$G$42,2,0),"") -> FRUTAS Y VERDURAS | Q336: =IFERROR(VLOOKUP(O336,PROVEEDORES!$A$3:$G$42,4,0),"") -> caseritaencasa@gmail.com | R336: =IFERROR(VLOOKUP(O336,PROVEEDORES!$A$3:$G$42,5,0),"") -> 56952069703 | S336: 7537 | T336: =AVERAGE(I336,N336,S336) -> 4369.3333 | U336: =T336*(1+$B$2) -> 4806.2667
A337: COLORANTES | B337: COLORANTE GEL ROJO | C337: UN | D337: 0.2 | E337: Bidfood Chile SA | F337: =IFERROR(VLOOKUP(E337,PROVEEDORES!$A$3:$G$42,2,0),"") -> ABARROTES | G337: =IFERROR(VLOOKUP(E337,PROVEEDORES!$A$3:$G$42,4,0),"") -> pagos@bidfood.cl,pmolina@bidfood.cl | H337: =IFERROR(VLOOKUP(E337,PROVEEDORES!$A$3:$G$42,5,0),"") -> 56225994444 - 56998038459 | I337: 3800 | J337: GOURMET SELECT LTDA | K337: =IFERROR(VLOOKUP(J337,PROVEEDORES!$A$3:$G$42,2,0),"") -> ESPECIES | L337: =IFERROR(VLOOKUP(J337,PROVEEDORES!$A$3:$G$42,4,0),"") -> chef@gourmetselect.cl,contabilidad@gourmetselect.cl,pedidos@gourmetselect.cl,info@gourmetselect.cl | M337: =IFERROR(VLOOKUP(J337,PROVEEDORES!$A$3:$G$42,5,0),"") -> 56944921093 | N337: 1224 | O337: CASERITA EN CASA SPA | P337: =IFERROR(VLOOKUP(O337,PROVEEDORES!$A$3:$G$42,2,0),"") -> FRUTAS Y VERDURAS | Q337: =IFERROR(VLOOKUP(O337,PROVEEDORES!$A$3:$G$42,4,0),"") -> caseritaencasa@gmail.com | R337: =IFERROR(VLOOKUP(O337,PROVEEDORES!$A$3:$G$42,5,0),"") -> 56952069703 | S337: 5614 | T337: =AVERAGE(I337,N337,S337) -> 3546 | U337: =T337*(1+$B$2) -> 3900.6
A338: COLORANTES | B338: COLORANTE HIDROSOLUBLE POLVO AMARILLO | C338: UN | D338: 0.068 | E338: Bidfood Chile SA | F338: =IFERROR(VLOOKUP(E338,PROVEEDORES!$A$3:$G$42,2,0),"") -> ABARROTES | G338: =IFERROR(VLOOKUP(E338,PROVEEDORES!$A$3:$G$42,4,0),"") -> pagos@bidfood.cl,pmolina@bidfood.cl | H338: =IFERROR(VLOOKUP(E338,PROVEEDORES!$A$3:$G$42,5,0),"") -> 56225994444 - 56998038459 | I338: 6840 | J338: GOURMET SELECT LTDA | K338: =IFERROR(VLOOKUP(J338,PROVEEDORES!$A$3:$G$42,2,0),"") -> ESPECIES | L338: =IFERROR(VLOOKUP(J338,PROVEEDORES!$A$3:$G$42,4,0),"") -> chef@gourmetselect.cl,contabilidad@gourmetselect.cl,pedidos@gourmetselect.cl,info@gourmetselect.cl | M338: =IFERROR(VLOOKUP(J338,PROVEEDORES!$A$3:$G$42,5,0),"") -> 56944921093 | N338: 3783 | O338: CASERITA EN CASA SPA | P338: =IFERROR(VLOOKUP(O338,PROVEEDORES!$A$3:$G$42,2,0),"") -> FRUTAS Y VERDURAS | Q338: =IFERROR(VLOOKUP(O338,PROVEEDORES!$A$3:$G$42,4,0),"") -> caseritaencasa@gmail.com | R338: =IFERROR(VLOOKUP(O338,PROVEEDORES!$A$3:$G$42,5,0),"") -> 56952069703 | S338: 8902 | T338: =AVERAGE(I338,N338,S338) -> 6508.3333 | U338: =T338*(1+$B$2) -> 7159.1667
A339: COLORANTES | B339: COLORANTE HIDROSOLUBLE POLVO ROJO | C339: UN | D339: 0.078 | E339: Bidfood Chile SA | F339: =IFERROR(VLOOKUP(E339,PROVEEDORES!$A$3:$G$42,2,0),"") -> ABARROTES | G339: =IFERROR(VLOOKUP(E339,PROVEEDORES!$A$3:$G$42,4,0),"") -> pagos@bidfood.cl,pmolina@bidfood.cl | H339: =IFERROR(VLOOKUP(E339,PROVEEDORES!$A$3:$G$42,5,0),"") -> 56225994444 - 56998038459 | I339: 9000 | J339: GOURMET SELECT LTDA | K339: =IFERROR(VLOOKUP(J339,PROVEEDORES!$A$3:$G$42,2,0),"") -> ESPECIES | L339: =IFERROR(VLOOKUP(J339,PROVEEDORES!$A$3:$G$42,4,0),"") -> chef@gourmetselect.cl,contabilidad@gourmetselect.cl,pedidos@gourmetselect.cl,info@gourmetselect.cl | M339: =IFERROR(VLOOKUP(J339,PROVEEDORES!$A$3:$G$42,5,0),"") -> 56944921093 | N339: 6462 | O339: CASERITA EN CASA SPA | P339: =IFERROR(VLOOKUP(O339,PROVEEDORES!$A$3:$G$42,2,0),"") -> FRUTAS Y VERDURAS | Q339: =IFERROR(VLOOKUP(O339,PROVEEDORES!$A$3:$G$42,4,0),"") -> caseritaencasa@gmail.com | R339: =IFERROR(VLOOKUP(O339,PROVEEDORES!$A$3:$G$42,5,0),"") -> 56952069703 | S339: 5179 | T339: =AVERAGE(I339,N339,S339) -> 6880.3333 | U339: =T339*(1+$B$2) -> 7568.3667
A340: COLORANTES | B340: COLORANTE HIDROSOLUBLE POLVO VERDE PISTACHO | C340: UN | D340: 0.065 | E340: Bidfood Chile SA | F340: =IFERROR(VLOOKUP(E340,PROVEEDORES!$A$3:$G$42,2,0),"") -> ABARROTES | G340: =IFERROR(VLOOKUP(E340,PROVEEDORES!$A$3:$G$42,4,0),"") -> pagos@bidfood.cl,pmolina@bidfood.cl | H340: =IFERROR(VLOOKUP(E340,PROVEEDORES!$A$3:$G$42,5,0),"") -> 56225994444 - 56998038459 | I340: 22770 | J340: GOURMET SELECT LTDA | K340: =IFERROR(VLOOKUP(J340,PROVEEDORES!$A$3:$G$42,2,0),"") -> ESPECIES | L340: =IFERROR(VLOOKUP(J340,PROVEEDORES!$A$3:$G$42,4,0),"") -> chef@gourmetselect.cl,contabilidad@gourmetselect.cl,pedidos@gourmetselect.cl,info@gourmetselect.cl | M340: =IFERROR(VLOOKUP(J340,PROVEEDORES!$A$3:$G$42,5,0),"") -> 56944921093 | N340: 22702 | O340: CASERITA EN CASA SPA | P340: =IFERROR(VLOOKUP(O340,PROVEEDORES!$A$3:$G$42,2,0),"") -> FRUTAS Y VERDURAS | Q340: =IFERROR(VLOOKUP(O340,PROVEEDORES!$A$3:$G$42,4,0),"") -> caseritaencasa@gmail.com | R340: =IFERROR(VLOOKUP(O340,PROVEEDORES!$A$3:$G$42,5,0),"") -> 56952069703 | S340: 17210 | T340: =AVERAGE(I340,N340,S340) -> 20894 | U340: =T340*(1+$B$2) -> 22983.4
A341: COLORANTES | B341: COLORANTE LIPO AMARILLO | C341: UN | D341: 0.03 | E341: Bidfood Chile SA | F341: =IFERROR(VLOOKUP(E341,PROVEEDORES!$A$3:$G$42,2,0),"") -> ABARROTES | G341: =IFERROR(VLOOKUP(E341,PROVEEDORES!$A$3:$G$42,4,0),"") -> pagos@bidfood.cl,pmolina@bidfood.cl | H341: =IFERROR(VLOOKUP(E341,PROVEEDORES!$A$3:$G$42,5,0),"") -> 56225994444 - 56998038459 | I341: 37600 | J341: GOURMET SELECT LTDA | K341: =IFERROR(VLOOKUP(J341,PROVEEDORES!$A$3:$G$42,2,0),"") -> ESPECIES | L341: =IFERROR(VLOOKUP(J341,PROVEEDORES!$A$3:$G$42,4,0),"") -> chef@gourmetselect.cl,contabilidad@gourmetselect.cl,pedidos@gourmetselect.cl,info@gourmetselect.cl | M341: =IFERROR(VLOOKUP(J341,PROVEEDORES!$A$3:$G$42,5,0),"") -> 56944921093 | N341: 45552 | O341: CASERITA EN CASA SPA | P341: =IFERROR(VLOOKUP(O341,PROVEEDORES!$A$3:$G$42,2,0),"") -> FRUTAS Y VERDURAS | Q341: =IFERROR(VLOOKUP(O341,PROVEEDORES!$A$3:$G$42,4,0),"") -> caseritaencasa@gmail.com | R341: =IFERROR(VLOOKUP(O341,PROVEEDORES!$A$3:$G$42,5,0),"") -> 56952069703 | S341: 69695 | T341: =AVERAGE(I341,N341,S341) -> 50949 | U341: =T341*(1+$B$2) -> 56043.9
A342: COLORANTES | B342: COLORANTE LIPO NARANJA POLVO 100GR | C342: UN | D342: 0.03 | E342: Bidfood Chile SA | F342: =IFERROR(VLOOKUP(E342,PROVEEDORES!$A$3:$G$42,2,0),"") -> ABARROTES | G342: =IFERROR(VLOOKUP(E342,PROVEEDORES!$A$3:$G$42,4,0),"") -> pagos@bidfood.cl,pmolina@bidfood.cl | H342: =IFERROR(VLOOKUP(E342,PROVEEDORES!$A$3:$G$42,5,0),"") -> 56225994444 - 56998038459 | I342: 22320 | J342: GOURMET SELECT LTDA | K342: =IFERROR(VLOOKUP(J342,PROVEEDORES!$A$3:$G$42,2,0),"") -> ESPECIES | L342: =IFERROR(VLOOKUP(J342,PROVEEDORES!$A$3:$G$42,4,0),"") -> chef@gourmetselect.cl,contabilidad@gourmetselect.cl,pedidos@gourmetselect.cl,info@gourmetselect.cl | M342: =IFERROR(VLOOKUP(J342,PROVEEDORES!$A$3:$G$42,5,0),"") -> 56944921093 | N342: 9832 | O342: CASERITA EN CASA SPA | P342: =IFERROR(VLOOKUP(O342,PROVEEDORES!$A$3:$G$42,2,0),"") -> FRUTAS Y VERDURAS | Q342: =IFERROR(VLOOKUP(O342,PROVEEDORES!$A$3:$G$42,4,0),"") -> caseritaencasa@gmail.com | R342: =IFERROR(VLOOKUP(O342,PROVEEDORES!$A$3:$G$42,5,0),"") -> 56952069703 | S342: 9848 | T342: =AVERAGE(I342,N342,S342) -> 14000 | U342: =T342*(1+$B$2) -> 15400
A343: COLORANTES | B343: COLORANTE LIPO ROJO POLVO 20GR | C343: UN | D343: 0.03 | E343: Bidfood Chile SA | F343: =IFERROR(VLOOKUP(E343,PROVEEDORES!$A$3:$G$42,2,0),"") -> ABARROTES | G343: =IFERROR(VLOOKUP(E343,PROVEEDORES!$A$3:$G$42,4,0),"") -> pagos@bidfood.cl,pmolina@bidfood.cl | H343: =IFERROR(VLOOKUP(E343,PROVEEDORES!$A$3:$G$42,5,0),"") -> 56225994444 - 56998038459 | I343: 6480 | J343: GOURMET SELECT LTDA | K343: =IFERROR(VLOOKUP(J343,PROVEEDORES!$A$3:$G$42,2,0),"") -> ESPECIES | L343: =IFERROR(VLOOKUP(J343,PROVEEDORES!$A$3:$G$42,4,0),"") -> chef@gourmetselect.cl,contabilidad@gourmetselect.cl,pedidos@gourmetselect.cl,info@gourmetselect.cl | M343: =IFERROR(VLOOKUP(J343,PROVEEDORES!$A$3:$G$42,5,0),"") -> 56944921093 | N343: 6772 | O343: CASERITA EN CASA SPA | P343: =IFERROR(VLOOKUP(O343,PROVEEDORES!$A$3:$G$42,2,0),"") -> FRUTAS Y VERDURAS | Q343: =IFERROR(VLOOKUP(O343,PROVEEDORES!$A$3:$G$42,4,0),"") -> caseritaencasa@gmail.com | R343: =IFERROR(VLOOKUP(O343,PROVEEDORES!$A$3:$G$42,5,0),"") -> 56952069703 | S343: 4484 | T343: =AVERAGE(I343,N343,S343) -> 5912 | U343: =T343*(1+$B$2) -> 6503.2
A344: COLORANTES | B344: COLORANTE LIPOSOLUBLE AMARILLO LIQUIDO | C344: UN | D344: 0.018 | E344: Bidfood Chile SA | F344: =IFERROR(VLOOKUP(E344,PROVEEDORES!$A$3:$G$42,2,0),"") -> ABARROTES | G344: =IFERROR(VLOOKUP(E344,PROVEEDORES!$A$3:$G$42,4,0),"") -> pagos@bidfood.cl,pmolina@bidfood.cl | H344: =IFERROR(VLOOKUP(E344,PROVEEDORES!$A$3:$G$42,5,0),"") -> 56225994444 - 56998038459 | I344: 20790 | J344: GOURMET SELECT LTDA | K344: =IFERROR(VLOOKUP(J344,PROVEEDORES!$A$3:$G$42,2,0),"") -> ESPECIES | L344: =IFERROR(VLOOKUP(J344,PROVEEDORES!$A$3:$G$42,4,0),"") -> chef@gourmetselect.cl,contabilidad@gourmetselect.cl,pedidos@gourmetselect.cl,info@gourmetselect.cl | M344: =IFERROR(VLOOKUP(J344,PROVEEDORES!$A$3:$G$42,5,0),"") -> 56944921093 | N344: 28742 | O344: CASERITA EN CASA SPA | P344: =IFERROR(VLOOKUP(O344,PROVEEDORES!$A$3:$G$42,2,0),"") -> FRUTAS Y VERDURAS | Q344: =IFERROR(VLOOKUP(O344,PROVEEDORES!$A$3:$G$42,4,0),"") -> caseritaencasa@gmail.com | R344: =IFERROR(VLOOKUP(O344,PROVEEDORES!$A$3:$G$42,5,0),"") -> 56952069703 | S344: 37530 | T344: =AVERAGE(I344,N344,S344) -> 29020.667 | U344: =T344*(1+$B$2) -> 31922.733
A345: COLORANTES | B345: COLORANTE LIPOSOLUBLE AZUL LIQUIDO | C345: UN | D345: 0.018 | E345: Bidfood Chile SA | F345: =IFERROR(VLOOKUP(E345,PROVEEDORES!$A$3:$G$42,2,0),"") -> ABARROTES | G345: =IFERROR(VLOOKUP(E345,PROVEEDORES!$A$3:$G$42,4,0),"") -> pagos@bidfood.cl,pmolina@bidfood.cl | H345: =IFERROR(VLOOKUP(E345,PROVEEDORES!$A$3:$G$42,5,0),"") -> 56225994444 - 56998038459 | I345: 16920 | J345: GOURMET SELECT LTDA | K345: =IFERROR(VLOOKUP(J345,PROVEEDORES!$A$3:$G$42,2,0),"") -> ESPECIES | L345: =IFERROR(VLOOKUP(J345,PROVEEDORES!$A$3:$G$42,4,0),"") -> chef@gourmetselect.cl,contabilidad@gourmetselect.cl,pedidos@gourmetselect.cl,info@gourmetselect.cl | M345: =IFERROR(VLOOKUP(J345,PROVEEDORES!$A$3:$G$42,5,0),"") -> 56944921093 | N345: 11895 | O345: CASERITA EN CASA SPA | P345: =IFERROR(VLOOKUP(O345,PROVEEDORES!$A$3:$G$42,2,0),"") -> FRUTAS Y VERDURAS | Q345: =IFERROR(VLOOKUP(O345,PROVEEDORES!$A$3:$G$42,4,0),"") -> caseritaencasa@gmail.com | R345: =IFERROR(VLOOKUP(O345,PROVEEDORES!$A$3:$G$42,5,0),"") -> 56952069703 | S345: 28757 | T345: =AVERAGE(I345,N345,S345) -> 19190.667 | U345: =T345*(1+$B$2) -> 21109.733
A346: COLORANTES | B346: COLORANTE LIPOSOLUBLE ROJO LIQUIDO | C346: UN | D346: 0.018 | E346: Bidfood Chile SA | F346: =IFERROR(VLOOKUP(E346,PROVEEDORES!$A$3:$G$42,2,0),"") -> ABARROTES | G346: =IFERROR(VLOOKUP(E346,PROVEEDORES!$A$3:$G$42,4,0),"") -> pagos@bidfood.cl,pmolina@bidfood.cl | H346: =IFERROR(VLOOKUP(E346,PROVEEDORES!$A$3:$G$42,5,0),"") -> 56225994444 - 56998038459 | I346: 16920 | J346: GOURMET SELECT LTDA | K346: =IFERROR(VLOOKUP(J346,PROVEEDORES!$A$3:$G$42,2,0),"") -> ESPECIES | L346: =IFERROR(VLOOKUP(J346,PROVEEDORES!$A$3:$G$42,4,0),"") -> chef@gourmetselect.cl,contabilidad@gourmetselect.cl,pedidos@gourmetselect.cl,info@gourmetselect.cl | M346: =IFERROR(VLOOKUP(J346,PROVEEDORES!$A$3:$G$42,5,0),"") -> 56944921093 | N346: 24534 | O346: CASERITA EN CASA SPA | P346: =IFERROR(VLOOKUP(O346,PROVEEDORES!$A$3:$G$42,2,0),"") -> FRUTAS Y VERDURAS | Q346: =IFERROR(VLOOKUP(O346,PROVEEDORES!$A$3:$G$42,4,0),"") -> caseritaencasa@gmail.com | R346: =IFERROR(VLOOKUP(O346,PROVEEDORES!$A$3:$G$42,5,0),"") -> 56952069703 | S346: 9252 | T346: =AVERAGE(I346,N346,S346) -> 16902 | U346: =T346*(1+$B$2) -> 18592.2
A347: COLORANTES | B347: COLORANTE LIPOSOLUBLE VERDE LIQUIDO | C347: UN | D347: 0.018 | E347: Bidfood Chile SA | F347: =IFERROR(VLOOKUP(E347,PROVEEDORES!$A$3:$G$42,2,0),"") -> ABARROTES | G347: =IFERROR(VLOOKUP(E347,PROVEEDORES!$A$3:$G$42,4,0),"") -> pagos@bidfood.cl,pmolina@bidfood.cl | H347: =IFERROR(VLOOKUP(E347,PROVEEDORES!$A$3:$G$42,5,0),"") -> 56225994444 - 56998038459 | I347: 18630 | J347: GOURMET SELECT LTDA | K347: =IFERROR(VLOOKUP(J347,PROVEEDORES!$A$3:$G$42,2,0),"") -> ESPECIES | L347: =IFERROR(VLOOKUP(J347,PROVEEDORES!$A$3:$G$42,4,0),"") -> chef@gourmetselect.cl,contabilidad@gourmetselect.cl,pedidos@gourmetselect.cl,info@gourmetselect.cl | M347: =IFERROR(VLOOKUP(J347,PROVEEDORES!$A$3:$G$42,5,0),"") -> 56944921093 | N347: 32351 | O347: CASERITA EN CASA SPA | P347: =IFERROR(VLOOKUP(O347,PROVEEDORES!$A$3:$G$42,2,0),"") -> FRUTAS Y VERDURAS | Q347: =IFERROR(VLOOKUP(O347,PROVEEDORES!$A$3:$G$42,4,0),"") -> caseritaencasa@gmail.com | R347: =IFERROR(VLOOKUP(O347,PROVEEDORES!$A$3:$G$42,5,0),"") -> 56952069703 | S347: 11990 | T347: =AVERAGE(I347,N347,S347) -> 20990.333 | U347: =T347*(1+$B$2) -> 23089.367
A348: COLORANTES | B348: COLORANTE METALICO ORO | C348: UN | D348: 0.015 | E348: Bidfood Chile SA | F348: =IFERROR(VLOOKUP(E348,PROVEEDORES!$A$3:$G$42,2,0),"") -> ABARROTES | G348: =IFERROR(VLOOKUP(E348,PROVEEDORES!$A$3:$G$42,4,0),"") -> pagos@bidfood.cl,pmolina@bidfood.cl | H348: =IFERROR(VLOOKUP(E348,PROVEEDORES!$A$3:$G$42,5,0),"") -> 56225994444 - 56998038459 | I348: 21960 | J348: GOURMET SELECT LTDA | K348: =IFERROR(VLOOKUP(J348,PROVEEDORES!$A$3:$G$42,2,0),"") -> ESPECIES | L348: =IFERROR(VLOOKUP(J348,PROVEEDORES!$A$3:$G$42,4,0),"") -> chef@gourmetselect.cl,contabilidad@gourmetselect.cl,pedidos@gourmetselect.cl,info@gourmetselect.cl | M348: =IFERROR(VLOOKUP(J348,PROVEEDORES!$A$3:$G$42,5,0),"") -> 56944921093 | N348: 26901 | O348: CASERITA EN CASA SPA | P348: =IFERROR(VLOOKUP(O348,PROVEEDORES!$A$3:$G$42,2,0),"") -> FRUTAS Y VERDURAS | Q348: =IFERROR(VLOOKUP(O348,PROVEEDORES!$A$3:$G$42,4,0),"") -> caseritaencasa@gmail.com | R348: =IFERROR(VLOOKUP(O348,PROVEEDORES!$A$3:$G$42,5,0),"") -> 56952069703 | S348: 33410 | T348: =AVERAGE(I348,N348,S348) -> 27423.667 | U348: =T348*(1+$B$2) -> 30166.033
A349: CONGELADO
A350: CONGELADO | B350: PASTA DE CHOCLO | C350: kg | D350: 0.215625 | E350: Bidfood Chile SA | F350: =IFERROR(VLOOKUP(E350,PROVEEDORES!$A$3:$G$42,2,0),"") -> ABARROTES | G350: =IFERROR(VLOOKUP(E350,PROVEEDORES!$A$3:$G$42,4,0),"") -> pagos@bidfood.cl,pmolina@bidfood.cl | H350: =IFERROR(VLOOKUP(E350,PROVEEDORES!$A$3:$G$42,5,0),"") -> 56225994444 - 56998038459 | I350: 2599 | J350: GOURMET SELECT LTDA | K350: =IFERROR(VLOOKUP(J350,PROVEEDORES!$A$3:$G$42,2,0),"") -> ESPECIES | L350: =IFERROR(VLOOKUP(J350,PROVEEDORES!$A$3:$G$42,4,0),"") -> chef@gourmetselect.cl,contabilidad@gourmetselect.cl,pedidos@gourmetselect.cl,info@gourmetselect.cl | M350: =IFERROR(VLOOKUP(J350,PROVEEDORES!$A$3:$G$42,5,0),"") -> 56944921093 | N350: 3199 | T350: =AVERAGE(I350,N350) -> 2899 | U350: =T350*(1+$B$2) -> 3188.9
A351: CONGELADO | B351: POROTOS VERDES CONGELADOS | C351: kg | D351: 0.195 | E351: Bidfood Chile SA | F351: =IFERROR(VLOOKUP(E351,PROVEEDORES!$A$3:$G$42,2,0),"") -> ABARROTES | G351: =IFERROR(VLOOKUP(E351,PROVEEDORES!$A$3:$G$42,4,0),"") -> pagos@bidfood.cl,pmolina@bidfood.cl | H351: =IFERROR(VLOOKUP(E351,PROVEEDORES!$A$3:$G$42,5,0),"") -> 56225994444 - 56998038459 | I351: 1471 | J351: GOURMET SELECT LTDA | K351: =IFERROR(VLOOKUP(J351,PROVEEDORES!$A$3:$G$42,2,0),"") -> ESPECIES | L351: =IFERROR(VLOOKUP(J351,PROVEEDORES!$A$3:$G$42,4,0),"") -> chef@gourmetselect.cl,contabilidad@gourmetselect.cl,pedidos@gourmetselect.cl,info@gourmetselect.cl | M351: =IFERROR(VLOOKUP(J351,PROVEEDORES!$A$3:$G$42,5,0),"") -> 56944921093 | N351: 1901 | T351: =AVERAGE(I351,N351) -> 1686 | U351: =T351*(1+$B$2) -> 1854.6
A352: CONGELADO | B352: PULPA DE CHIRIMOYA | C352: kg | D352: 0.18 | E352: Bidfood Chile SA | F352: =IFERROR(VLOOKUP(E352,PROVEEDORES!$A$3:$G$42,2,0),"") -> ABARROTES | G352: =IFERROR(VLOOKUP(E352,PROVEEDORES!$A$3:$G$42,4,0),"") -> pagos@bidfood.cl,pmolina@bidfood.cl | H352: =IFERROR(VLOOKUP(E352,PROVEEDORES!$A$3:$G$42,5,0),"") -> 56225994444 - 56998038459 | I352: 5361 | J352: GOURMET SELECT LTDA | K352: =IFERROR(VLOOKUP(J352,PROVEEDORES!$A$3:$G$42,2,0),"") -> ESPECIES | L352: =IFERROR(VLOOKUP(J352,PROVEEDORES!$A$3:$G$42,4,0),"") -> chef@gourmetselect.cl,contabilidad@gourmetselect.cl,pedidos@gourmetselect.cl,info@gourmetselect.cl | M352: =IFERROR(VLOOKUP(J352,PROVEEDORES!$A$3:$G$42,5,0),"") -> 56944921093 | N352: 8948 | T352: =AVERAGE(I352,N352) -> 7154.5 | U352: =T352*(1+$B$2) -> 7869.95
A353: CONGELADO | B353: PULPA DE DURAZNO | C353: kg | D353: 0.13 | E353: Bidfood Chile SA | F353: =IFERROR(VLOOKUP(E353,PROVEEDORES!$A$3:$G$42,2,0),"") -> ABARROTES | G353: =IFERROR(VLOOKUP(E353,PROVEEDORES!$A$3:$G$42,4,0),"") -> pagos@bidfood.cl,pmolina@bidfood.cl | H353: =IFERROR(VLOOKUP(E353,PROVEEDORES!$A$3:$G$42,5,0),"") -> 56225994444 - 56998038459 | I353: 2970 | J353: GOURMET SELECT LTDA | K353: =IFERROR(VLOOKUP(J353,PROVEEDORES!$A$3:$G$42,2,0),"") -> ESPECIES | L353: =IFERROR(VLOOKUP(J353,PROVEEDORES!$A$3:$G$42,4,0),"") -> chef@gourmetselect.cl,contabilidad@gourmetselect.cl,pedidos@gourmetselect.cl,info@gourmetselect.cl | M353: =IFERROR(VLOOKUP(J353,PROVEEDORES!$A$3:$G$42,5,0),"") -> 56944921093 | N353: 3683 | T353: =AVERAGE(I353,N353) -> 3326.5 | U353: =T353*(1+$B$2) -> 3659.15
A354: CONGELADO | B354: PULPA DE FRAMBUESA | C354: kg | D354: 0.06 | E354: Bidfood Chile SA | F354: =IFERROR(VLOOKUP(E354,PROVEEDORES!$A$3:$G$42,2,0),"") -> ABARROTES | G354: =IFERROR(VLOOKUP(E354,PROVEEDORES!$A$3:$G$42,4,0),"") -> pagos@bidfood.cl,pmolina@bidfood.cl | H354: =IFERROR(VLOOKUP(E354,PROVEEDORES!$A$3:$G$42,5,0),"") -> 56225994444 - 56998038459 | I354: 6029 | J354: GOURMET SELECT LTDA | K354: =IFERROR(VLOOKUP(J354,PROVEEDORES!$A$3:$G$42,2,0),"") -> ESPECIES | L354: =IFERROR(VLOOKUP(J354,PROVEEDORES!$A$3:$G$42,4,0),"") -> chef@gourmetselect.cl,contabilidad@gourmetselect.cl,pedidos@gourmetselect.cl,info@gourmetselect.cl | M354: =IFERROR(VLOOKUP(J354,PROVEEDORES!$A$3:$G$42,5,0),"") -> 56944921093 | N354: 9891 | T354: =AVERAGE(I354,N354) -> 7960 | U354: =T354*(1+$B$2) -> 8756
A355: CONGELADO | B355: PULPA DE FRAMBUESA S/AZUCAR | C355: kg | D355: 0.664375 | E355: Bidfood Chile SA | F355: =IFERROR(VLOOKUP(E355,PROVEEDORES!$A$3:$G$42,2,0),"") -> ABARROTES | G355: =IFERROR(VLOOKUP(E355,PROVEEDORES!$A$3:$G$42,4,0),"") -> pagos@bidfood.cl,pmolina@bidfood.cl | H355: =IFERROR(VLOOKUP(E355,PROVEEDORES!$A$3:$G$42,5,0),"") -> 56225994444 - 56998038459 | I355: 5895 | J355: GOURMET SELECT LTDA | K355: =IFERROR(VLOOKUP(J355,PROVEEDORES!$A$3:$G$42,2,0),"") -> ESPECIES | L355: =IFERROR(VLOOKUP(J355,PROVEEDORES!$A$3:$G$42,4,0),"") -> chef@gourmetselect.cl,contabilidad@gourmetselect.cl,pedidos@gourmetselect.cl,info@gourmetselect.cl | M355: =IFERROR(VLOOKUP(J355,PROVEEDORES!$A$3:$G$42,5,0),"") -> 56944921093 | N355: 1987 | T355: =AVERAGE(I355,N355) -> 3941 | U355: =T355*(1+$B$2) -> 4335.1
A356: CONGELADO | B356: PULPA DE FRUTILLA | C356: kg | D356: 0.33 | E356: Bidfood Chile SA | F356: =IFERROR(VLOOKUP(E356,PROVEEDORES!$A$3:$G$42,2,0),"") -> ABARROTES | G356: =IFERROR(VLOOKUP(E356,PROVEEDORES!$A$3:$G$42,4,0),"") -> pagos@bidfood.cl,pmolina@bidfood.cl | H356: =IFERROR(VLOOKUP(E356,PROVEEDORES!$A$3:$G$42,5,0),"") -> 56225994444 - 56998038459 | I356: 2972 | J356: GOURMET SELECT LTDA | K356: =IFERROR(VLOOKUP(J356,PROVEEDORES!$A$3:$G$42,2,0),"") -> ESPECIES | L356: =IFERROR(VLOOKUP(J356,PROVEEDORES!$A$3:$G$42,4,0),"") -> chef@gourmetselect.cl,contabilidad@gourmetselect.cl,pedidos@gourmetselect.cl,info@gourmetselect.cl | M356: =IFERROR(VLOOKUP(J356,PROVEEDORES!$A$3:$G$42,5,0),"") -> 56944921093 | N356: 4292 | T356: =AVERAGE(I356,N356) -> 3632 | U356: =T356*(1+$B$2) -> 3995.2
A357: CONGELADO | B357: PULPA DE FRUTILLA S/AZUCAR | C357: kg | D357: 0.125 | E357: Bidfood Chile SA | F357: =IFERROR(VLOOKUP(E357,PROVEEDORES!$A$3:$G$42,2,0),"") -> ABARROTES | G357: =IFERROR(VLOOKUP(E357,PROVEEDORES!$A$3:$G$42,4,0),"") -> pagos@bidfood.cl,pmolina@bidfood.cl | H357: =IFERROR(VLOOKUP(E357,PROVEEDORES!$A$3:$G$42,5,0),"") -> 56225994444 - 56998038459 | I357: 4500 | J357: GOURMET SELECT LTDA | K357: =IFERROR(VLOOKUP(J357,PROVEEDORES!$A$3:$G$42,2,0),"") -> ESPECIES | L357: =IFERROR(VLOOKUP(J357,PROVEEDORES!$A$3:$G$42,4,0),"") -> chef@gourmetselect.cl,contabilidad@gourmetselect.cl,pedidos@gourmetselect.cl,info@gourmetselect.cl | M357: =IFERROR(VLOOKUP(J357,PROVEEDORES!$A$3:$G$42,5,0),"") -> 56944921093 | N357: 7463 | T357: =AVERAGE(I357,N357) -> 5981.5 | U357: =T357*(1+$B$2) -> 6579.65
A358: CONGELADO | B358: PULPA DE MANGO | C358: kg | D358: 0.2175 | E358: Bidfood Chile SA | F358: =IFERROR(VLOOKUP(E358,PROVEEDORES!$A$3:$G$42,2,0),"") -> ABARROTES | G358: =IFERROR(VLOOKUP(E358,PROVEEDORES!$A$3:$G$42,4,0),"") -> pagos@bidfood.cl,pmolina@bidfood.cl | H358: =IFERROR(VLOOKUP(E358,PROVEEDORES!$A$3:$G$42,5,0),"") -> 56225994444 - 56998038459 | I358: 5865 | J358: GOURMET SELECT LTDA | K358: =IFERROR(VLOOKUP(J358,PROVEEDORES!$A$3:$G$42,2,0),"") -> ESPECIES | L358: =IFERROR(VLOOKUP(J358,PROVEEDORES!$A$3:$G$42,4,0),"") -> chef@gourmetselect.cl,contabilidad@gourmetselect.cl,pedidos@gourmetselect.cl,info@gourmetselect.cl | M358: =IFERROR(VLOOKUP(J358,PROVEEDORES!$A$3:$G$42,5,0),"") -> 56944921093 | N358: 2091 | T358: =AVERAGE(I358,N358) -> 3978 | U358: =T358*(1+$B$2) -> 4375.8
A359: CONGELADO | B359: PULPA DE MANGO S/AZUCAR | C359: kg | D359: 0.145 | E359: Bidfood Chile SA | F359: =IFERROR(VLOOKUP(E359,PROVEEDORES!$A$3:$G$42,2,0),"") -> ABARROTES | G359: =IFERROR(VLOOKUP(E359,PROVEEDORES!$A$3:$G$42,4,0),"") -> pagos@bidfood.cl,pmolina@bidfood.cl | H359: =IFERROR(VLOOKUP(E359,PROVEEDORES!$A$3:$G$42,5,0),"") -> 56225994444 - 56998038459 | I359: 6500 | J359: GOURMET SELECT LTDA | K359: =IFERROR(VLOOKUP(J359,PROVEEDORES!$A$3:$G$42,2,0),"") -> ESPECIES | L359: =IFERROR(VLOOKUP(J359,PROVEEDORES!$A$3:$G$42,4,0),"") -> chef@gourmetselect.cl,contabilidad@gourmetselect.cl,pedidos@gourmetselect.cl,info@gourmetselect.cl | M359: =IFERROR(VLOOKUP(J359,PROVEEDORES!$A$3:$G$42,5,0),"") -> 56944921093 | N359: 8606 | T359: =AVERAGE(I359,N359) -> 7553 | U359: =T359*(1+$B$2) -> 8308.3
A360: CONGELADO | B360: PULPA DE MARACUYA S/AZUCAR | C360: kg | D360: 0.2 | E360: Bidfood Chile SA | F360: =IFERROR(VLOOKUP(E360,PROVEEDORES!$A$3:$G$42,2,0),"") -> ABARROTES | G360: =IFERROR(VLOOKUP(E360,PROVEEDORES!$A$3:$G$42,4,0),"") -> pagos@bidfood.cl,pmolina@bidfood.cl | H360: =IFERROR(VLOOKUP(E360,PROVEEDORES!$A$3:$G$42,5,0),"") -> 56225994444 - 56998038459 | I360: 8028 | J360: GOURMET SELECT LTDA | K360: =IFERROR(VLOOKUP(J360,PROVEEDORES!$A$3:$G$42,2,0),"") -> ESPECIES | L360: =IFERROR(VLOOKUP(J360,PROVEEDORES!$A$3:$G$42,4,0),"") -> chef@gourmetselect.cl,contabilidad@gourmetselect.cl,pedidos@gourmetselect.cl,info@gourmetselect.cl | M360: =IFERROR(VLOOKUP(J360,PROVEEDORES!$A$3:$G$42,5,0),"") -> 56944921093 | N360: 2717 | T360: =AVERAGE(I360,N360) -> 5372.5 | U360: =T360*(1+$B$2) -> 5909.75
A361: CONGELADO | B361: PULPA DE MARACUYA SIN SEMILLA | C361: kg | D361: 0.33775 | E361: Bidfood Chile SA | F361: =IFERROR(VLOOKUP(E361,PROVEEDORES!$A$3:$G$42,2,0),"") -> ABARROTES | G361: =IFERROR(VLOOKUP(E361,PROVEEDORES!$A$3:$G$42,4,0),"") -> pagos@bidfood.cl,pmolina@bidfood.cl | H361: =IFERROR(VLOOKUP(E361,PROVEEDORES!$A$3:$G$42,5,0),"") -> 56225994444 - 56998038459 | I361: 8028 | J361: GOURMET SELECT LTDA | K361: =IFERROR(VLOOKUP(J361,PROVEEDORES!$A$3:$G$42,2,0),"") -> ESPECIES | L361: =IFERROR(VLOOKUP(J361,PROVEEDORES!$A$3:$G$42,4,0),"") -> chef@gourmetselect.cl,contabilidad@gourmetselect.cl,pedidos@gourmetselect.cl,info@gourmetselect.cl | M361: =IFERROR(VLOOKUP(J361,PROVEEDORES!$A$3:$G$42,5,0),"") -> 56944921093 | N361: 13567 | T361: =AVERAGE(I361,N361) -> 10797.5 | U361: =T361*(1+$B$2) -> 11877.25
A362: CONGELADO | B362: PULPA DE MELON TUNA | C362: kg | D362: 0.025 | E362: Bidfood Chile SA | F362: =IFERROR(VLOOKUP(E362,PROVEEDORES!$A$3:$G$42,2,0),"") -> ABARROTES | G362: =IFERROR(VLOOKUP(E362,PROVEEDORES!$A$3:$G$42,4,0),"") -> pagos@bidfood.cl,pmolina@bidfood.cl | H362: =IFERROR(VLOOKUP(E362,PROVEEDORES!$A$3:$G$42,5,0),"") -> 56225994444 - 56998038459 | I362: 4709 | J362: GOURMET SELECT LTDA | K362: =IFERROR(VLOOKUP(J362,PROVEEDORES!$A$3:$G$42,2,0),"") -> ESPECIES | L362: =IFERROR(VLOOKUP(J362,PROVEEDORES!$A$3:$G$42,4,0),"") -> chef@gourmetselect.cl,contabilidad@gourmetselect.cl,pedidos@gourmetselect.cl,info@gourmetselect.cl | M362: =IFERROR(VLOOKUP(J362,PROVEEDORES!$A$3:$G$42,5,0),"") -> 56944921093 | N362: 4603 | T362: =AVERAGE(I362,N362) -> 4656 | U362: =T362*(1+$B$2) -> 5121.6
A363: CONSERVA
A364: CONSERVA | B364: GARBANZOS EN CONSERVA WASIL 380 GR | C364: UN | D364: 0.1 | E364: Bidfood Chile SA | F364: =IFERROR(VLOOKUP(E364,PROVEEDORES!$A$3:$G$42,2,0),"") -> ABARROTES | G364: =IFERROR(VLOOKUP(E364,PROVEEDORES!$A$3:$G$42,4,0),"") -> pagos@bidfood.cl,pmolina@bidfood.cl | H364: =IFERROR(VLOOKUP(E364,PROVEEDORES!$A$3:$G$42,5,0),"") -> 56225994444 - 56998038459 | I364: 1460 | J364: GOURMET SELECT LTDA | K364: =IFERROR(VLOOKUP(J364,PROVEEDORES!$A$3:$G$42,2,0),"") -> ESPECIES | L364: =IFERROR(VLOOKUP(J364,PROVEEDORES!$A$3:$G$42,4,0),"") -> chef@gourmetselect.cl,contabilidad@gourmetselect.cl,pedidos@gourmetselect.cl,info@gourmetselect.cl | M364: =IFERROR(VLOOKUP(J364,PROVEEDORES!$A$3:$G$42,5,0),"") -> 56944921093 | N364: 1138 | O364: CASERITA EN CASA SPA | P364: =IFERROR(VLOOKUP(O364,PROVEEDORES!$A$3:$G$42,2,0),"") -> FRUTAS Y VERDURAS | Q364: =IFERROR(VLOOKUP(O364,PROVEEDORES!$A$3:$G$42,4,0),"") -> caseritaencasa@gmail.com | R364: =IFERROR(VLOOKUP(O364,PROVEEDORES!$A$3:$G$42,5,0),"") -> 56952069703 | S364: 1810 | T364: =AVERAGE(I364,N364,S364) -> 1469.3333 | U364: =T364*(1+$B$2) -> 1616.2667
...

Sheet RESUMEN
A1: RESUMEN POR CATEGORIA
A2: CATEGORÍA | B2: N° PRODUCTOS | C2: COSTO PROM. ESTIMADO | D2: COSTO TOTAL ESTIMADO
A3: ABARROTE | B3: =COUNTIF('CONSOLIDADO PRECIOS'!$A$5:$A$646,A3) -> 240 | C3: =IFERROR(AVERAGEIF('CONSOLIDADO PRECIOS'!$A$5:$A$646,A3,'CONSOLIDADO PRECIOS'!$U$5:$U$646),0) -> 18165.546 | D3: =SUMIF('CONSOLIDADO PRECIOS'!$A$5:$A$646,A3,'CONSOLIDADO PRECIOS'!$U$5:$U$646) -> 4341565.4
A4: AGUA | B4: =COUNTIF('CONSOLIDADO PRECIOS'!$A$5:$A$646,A4) -> 3 | C4: =IFERROR(AVERAGEIF('CONSOLIDADO PRECIOS'!$A$5:$A$646,A4,'CONSOLIDADO PRECIOS'!$U$5:$U$646),0) -> 7667 | D4: =SUMIF('CONSOLIDADO PRECIOS'!$A$5:$A$646,A4,'CONSOLIDADO PRECIOS'!$U$5:$U$646) -> 15334
A5: ALGAS | B5: =COUNTIF('CONSOLIDADO PRECIOS'!$A$5:$A$646,A5) -> 2 | C5: =IFERROR(AVERAGEIF('CONSOLIDADO PRECIOS'!$A$5:$A$646,A5,'CONSOLIDADO PRECIOS'!$U$5:$U$646),0) -> 9824.8333 | D5: =SUMIF('CONSOLIDADO PRECIOS'!$A$5:$A$646,A5,'CONSOLIDADO PRECIOS'!$U$5:$U$646) -> 9824.8333
A6: ARTICULO COCINA | B6: =COUNTIF('CONSOLIDADO PRECIOS'!$A$5:$A$646,A6) -> 35 | C6: =IFERROR(AVERAGEIF('CONSOLIDADO PRECIOS'!$A$5:$A$646,A6,'CONSOLIDADO PRECIOS'!$U$5:$U$646),0) -> 2572.2529 | D6: =SUMIF('CONSOLIDADO PRECIOS'!$A$5:$A$646,A6,'CONSOLIDADO PRECIOS'!$U$5:$U$646) -> 87456.6
A7: BROTES | B7: =COUNTIF('CONSOLIDADO PRECIOS'!$A$5:$A$646,A7) -> 2 | C7: =IFERROR(AVERAGEIF('CONSOLIDADO PRECIOS'!$A$5:$A$646,A7,'CONSOLIDADO PRECIOS'!$U$5:$U$646),0) -> 3575.3667 | D7: =SUMIF('CONSOLIDADO PRECIOS'!$A$5:$A$646,A7,'CONSOLIDADO PRECIOS'!$U$5:$U$646) -> 3575.3667
A8: CABRITO | B8: =COUNTIF('CONSOLIDADO PRECIOS'!$A$5:$A$646,A8) -> 2 | C8: =IFERROR(AVERAGEIF('CONSOLIDADO PRECIOS'!$A$5:$A$646,A8,'CONSOLIDADO PRECIOS'!$U$5:$U$646),0) -> 24334.567 | D8: =SUMIF('CONSOLIDADO PRECIOS'!$A$5:$A$646,A8,'CONSOLIDADO PRECIOS'!$U$5:$U$646) -> 24334.567
A9: CERDO | B9: =COUNTIF('CONSOLIDADO PRECIOS'!$A$5:$A$646,A9) -> 22 | C9: =IFERROR(AVERAGEIF('CONSOLIDADO PRECIOS'!$A$5:$A$646,A9,'CONSOLIDADO PRECIOS'!$U$5:$U$646),0) -> 14539.905 | D9: =SUMIF('CONSOLIDADO PRECIOS'!$A$5:$A$646,A9,'CONSOLIDADO PRECIOS'!$U$5:$U$646) -> 305338
A10: CERVEZA | B10: =COUNTIF('CONSOLIDADO PRECIOS'!$A$5:$A$646,A10) -> 2 | C10: =IFERROR(AVERAGEIF('CONSOLIDADO PRECIOS'!$A$5:$A$646,A10,'CONSOLIDADO PRECIOS'!$U$5:$U$646),0) -> 5725.5 | D10: =SUMIF('CONSOLIDADO PRECIOS'!$A$5:$A$646,A10,'CONSOLIDADO PRECIOS'!$U$5:$U$646) -> 5725.5
A11: CHOCOLATE | B11: =COUNTIF('CONSOLIDADO PRECIOS'!$A$5:$A$646,A11) -> 22 | C11: =IFERROR(AVERAGEIF('CONSOLIDADO PRECIOS'!$A$5:$A$646,A11,'CONSOLIDADO PRECIOS'!$U$5:$U$646),0) -> 17098.417 | D11: =SUMIF('CONSOLIDADO PRECIOS'!$A$5:$A$646,A11,'CONSOLIDADO PRECIOS'!$U$5:$U$646) -> 359066.77
A12: COLORANTES | B12: =COUNTIF('CONSOLIDADO PRECIOS'!$A$5:$A$646,A12) -> 14 | C12: =IFERROR(AVERAGEIF('CONSOLIDADO PRECIOS'!$A$5:$A$646,A12,'CONSOLIDADO PRECIOS'!$U$5:$U$646),0) -> 19172.69 | D12: =SUMIF('CONSOLIDADO PRECIOS'!$A$5:$A$646,A12,'CONSOLIDADO PRECIOS'!$U$5:$U$646) -> 249244.97
A13: CONGELADO | B13: =COUNTIF('CONSOLIDADO PRECIOS'!$A$5:$A$646,A13) -> 14 | C13: =IFERROR(AVERAGEIF('CONSOLIDADO PRECIOS'!$A$5:$A$646,A13,'CONSOLIDADO PRECIOS'!$U$5:$U$646),0) -> 5833.1731 | D13: =SUMIF('CONSOLIDADO PRECIOS'!$A$5:$A$646,A13,'CONSOLIDADO PRECIOS'!$U$5:$U$646) -> 75831.25
A14: CONSERVA | B14: =COUNTIF('CONSOLIDADO PRECIOS'!$A$5:$A$646,A14) -> 5 | C14: =IFERROR(AVERAGEIF('CONSOLIDADO PRECIOS'!$A$5:$A$646,A14,'CONSOLIDADO PRECIOS'!$U$5:$U$646),0) -> 5490.5583 | D14: =SUMIF('CONSOLIDADO PRECIOS'!$A$5:$A$646,A14,'CONSOLIDADO PRECIOS'!$U$5:$U$646) -> 21962.233
... A36: YOGURT | B36: =COUNTIF('CONSOLIDADO PRECIOS'!$A$5:$A$646,A36) -> 4 | C36: =IFERROR(AVERAGEIF('CONSOLIDADO PRECIOS'!$A$5:$A$646,A36,'CONSOLIDADO PRECIOS'!$U$5:$U$646),0) -> 3064.8444 | D36: =SUMIF('CONSOLIDADO PRECIOS'!$A$5:$A$646,A36,'CONSOLIDADO PRECIOS'!$U$5:$U$646) -> 9194.5333
A37: TOTAL | B37: =SUM(B3:B36) -> 642 | D37: =SUM(D3:D36) -> 8279311.2
